Workbook
Name multiply: 'BUDGET COMMERCIALE'!#REF!
Name p: 'BUDGET COMMERCIALE'!#REF!

Sheet BUDGET COMMERCIALE
B1: Budget del settore distributivo - SETTORE CALZATURIERO
A2: PIANO DEI VOLUMI DI VENDITA | Z2: Tabella delle informazioni commerciali
A3: LUREX 1 | B3: GEN. | C3: FEB. | D3: MAR. | E3: I TRIM | F3: APR. | G3: MAG. | H3: GIU. | I3: II TRIM | J3: LUG. | K3: AGO | L3: SET | M3: III TRIM | N3: OTT. | O3: NOV. | P3: DIC. | Q3: IV TRIM. | R3: TOTALE | V3: LUREX | X3: prodotti | Y3: Italia | AA3: Francia
A4: Italia | V4: Sconti | Y4: I semestre | Z4: II semestre | AA4: I semestre | AB4: II semestre
A5: Moccassino | B5: 6000 | C5: 5500 | D5: 6000 | E5: =B5+C5+D5 -> 17500 | F5: 6000 | G5: 6500 | H5: 7000 | I5: =SUM(F5:H5) -> 19500 | J5: 6800 | K5: 6350 | L5: 6200 | M5: =SUM(J5:L5) -> 19350 | N5: 5860 | O5: 5420 | P5: 5000 | Q5: =SUM(N5:P5) -> 16280 | R5: =Q5+M5+I5+E5 -> 72630 | V5: Mocassino | Y5: 0.02 | Z5: 0.02 | AA5: 0.03 | AB5: 0.03
A6: Decollete' | B6: 6000 | C6: 5500 | D6: 6000 | E6: =B6+C6+D6 -> 17500 | F6: 5800 | G6: 6100 | H6: 6730 | I6: =SUM(F6:H6) -> 18630 | J6: 6560 | K6: 6100 | L6: 5960 | M6: 18620 | N6: 6000 | O6: 5740 | P6: 5380 | Q6: =SUM(N6:P6) -> 17120 | R6: =Q6+M6+I6+E6 -> 71870 | V6: Decollete' | Y6: 0.03 | Z6: 0.03 | AA6: 0.05 | AB6: 0.05
A7: All star | B7: 2000 | C7: 2000 | D7: 2500 | E7: =B7+C7+D7 -> 6500 | F7: 3350 | G7: 3860 | H7: 4100 | I7: =SUM(F7:H7) -> 11310 | J7: 3900 | K7: 4050 | L7: 3800 | M7: 11750 | N7: 3150 | O7: 2890 | P7: 2120 | Q7: =SUM(N7:P7) -> 8160 | R7: =Q7+M7+I7+E7 -> 37720 | V7: All star | Y7: 0.04 | Z7: 0.04
A8: Slip on in pelle | B8: 640 | C8: 640 | D8: 780 | E8: =SUM(B8:D8) -> 2060 | F8: 1060 | G8: 1240 | H8: 1320 | I8: =SUM(F8:H8) -> 3620 | J8: 1240 | K8: 1280 | L8: 1200 | M8: =SUM(J8:L8) -> 3720 | N8: 1000 | O8: 920 | P8: 1000 | Q8: =SUM(N8:P8) -> 2920 | R8: =Q8+M8+I8+E8 -> 12320 | V8: Slip on in pelle | Y8: 0.03 | Z8: 0.03
A9: Francia
A10: Moccassino | B10: 3800 | C10: 4000 | D10: 4400 | E10: =B10+C10+D10 -> 12200 | F10: 4750 | G10: 5200 | H10: 5430 | I10: =SUM(F10:H10) -> 15380 | J10: 5860 | K10: 5780 | L10: 5420 | M10: 17060 | N10: 4980 | O10: 4310 | P10: 3860 | Q10: 13150 | R10: =Q10+M10+I10+E10 -> 57790
A11: Decollete' | B11: 1300 | C11: 1400 | D11: 1800 | E11: =B11+C11+D11 -> 4500 | F11: 1970 | G11: 2350 | H11: 2560 | I11: =SUM(F11:H11) -> 6880 | J11: 2890 | K11: 3000 | L11: 2640 | M11: 8530 | N11: 2210 | O11: 1900 | P11: 1560 | Q11: 5670 | R11: =Q11+M11+I11+E11 -> 25580
V12: Costi unitari trasporto | X12: Mocassino | Y12: 0.3 | Z12: 0.35 | AA12: 0.5 | AB12: 0.55
X13: Decollete' | Y13: 0.3 | Z13: 0.35 | AA13: 0.5 | AB13: 0.55
X14: All star | Y14: 0.3 | Z14: 0.35
A15: PREZZI DI VENDITA | X15: Slip on in pelle | Y15: 0.3 | Z15: 0.3
A16: LUREX | B16: Italia | D16: Estero
B17: I semestre | C17: II semestre | D17: I semestre | E17: II semestre
A18: Mocassino | B18: 40 | C18: 40 | D18: 40 | E18: 40
A19: Decollete' | B19: 50 | C19: 50 | D19: 50 | E19: 50 | V19: provvigioni esterne | X19: Mocassino | Y19: 0.02 | Z19: 0.02 | AA19: 0.03 | AB19: 0.03
A20: All star | B20: 30 | C20: 30 | X20: Decollete' | Y20: 0.02 | Z20: 0.02 | AA20: 0.03 | AB20: 0.03
A21: Slip on in pelle | B21: 40 | C21: 40 | X21: All star | Y21: 0.02 | Z21: 0.02
X22: slip on in pelle | Y22: 0.02 | Z22: 0.02
A24: BUDGET DEI RICAVI TEORICI
A25: LUREX 1 | B25: GEN. | C25: FEB. | D25: MAR. | E25: I TRIM | F25: APR. | G25: MAG. | H25: GIU. | I25: II TRIM | J25: LUG. | K25: AGO | L25: SET | M25: III TRIM | N25: OTT. | O25: NOV. | P25: DIC. | Q25: IV TRIM. | R25: TOTALE
A26: Italia
A27: Moccassino | B27: =B5*B18 -> 240000 | C27: =C5*B18 -> 220000 | D27: =D5*B18 -> 240000 | E27: 700000 | F27: =F5*B18 -> 240000 | G27: =G5*B18 -> 260000 | H27: =H5*B18 -> 280000 | I27: =SUM(F27:H27) -> 780000 | J27: =J5*C18 -> 272000 | K27: =K5*C18 -> 254000 | L27: =L5*C18 -> 248000 | M27: =SUM(J27:L27) -> 774000 | N27: =N5*C18 -> 234400 | O27: =O5*C18 -> 216800 | P27: =P5*C18 -> 200000 | Q27: =SUM(N27:P27) -> 651200 | R27: =Q27+M27+I27+E27 -> 2905200
A28: Decollete' | B28: =B6*B19 -> 300000 | C28: =C6*B19 -> 275000 | D28: =D6*B19 -> 300000 | E28: 875000 | F28: =F6*B19 -> 290000 | G28: =G6*B19 -> 305000 | H28: =H6*B19 -> 336500 | I28: =SUM(F28:H28) -> 931500 | J28: =J6*C19 -> 328000 | K28: =K6*C19 -> 305000 | L28: =L6*C19 -> 298000 | M28: =SUM(J28:L28) -> 931000 | N28: =N6*C19 -> 300000 | O28: =SUM(O6*C19) -> 287000 | P28: =P6*C19 -> 269000 | Q28: =SUM(N28:P28) -> 856000 | R28: =Q28+M28+I28+E28 -> 3593500
A29: All star | B29: =B7*B20 -> 60000 | C29: =C7*B20 -> 60000 | D29: =D7*B20 -> 75000 | E29: 195000 | F29: =F7*B20 -> 100500 | G29: =G7*B20 -> 115800 | H29: =H7*B20 -> 123000 | I29: =SUM(F29:H29) -> 339300 | J29: =J7*C20 -> 117000 | K29: =K7*C20 -> 121500 | L29: =L7*C20 -> 114000 | M29: =SUM(J29:L29) -> 352500 | N29: =N7*C20 -> 94500 | O29: =O7*C20 -> 86700 | P29: =P7*C20 -> 63600 | Q29: =SUM(N29:P29) -> 244800 | R29: =Q29+M29+I29+E29 -> 1131600
A30: Slip on in pelle | B30: =B8*B21 -> 25600 | C30: =C8*B21 -> 25600 | D30: =D8*B21 -> 31200 | E30: =SUM(B30:D30) -> 82400 | F30: =F8*B21 -> 42400 | G30: =G8*B21 -> 49600 | H30: =H8*B21 -> 52800 | I30: =SUM(F30:H30) -> 144800 | J30: =J8*C21 -> 49600 | K30: =K8*C21 -> 51200 | L30: =L8*C21 -> 48000 | M30: =SUM(J30:L30) -> 148800 | N30: =N8*C21 -> 40000 | O30: =O8*C21 -> 36800 | P30: =P8*C21 -> 40000 | Q30: =SUM(N30:P30) -> 116800 | R30: =Q30+M30+I30+E30 -> 492800
A31: Totale | B31: =B27+B28+B29+B30 -> 625600 | C31: =C27+C28+C29+C30 -> 580600 | D31: =D27+D28+D29+D30 -> 646200 | E31: =E27+E28+E29+E30 -> 1852400 | F31: =SUM(F27:F30) -> 672900 | G31: =SUM(G27:G30) -> 730400 | H31: =SUM(H27:H30) -> 792300 | I31: =SUM(I27:I30) -> 2195600 | J31: =SUM(J27:J30) -> 766600 | K31: =SUM(K27:K30) -> 731700 | L31: =SUM(L27:L30) -> 708000 | M31: =SUM(M27:M30) -> 2206300 | ... Q31: =SUM(Q27:Q30) -> 1868800 | R31: =SUM(Q31+M31+I31+E31) -> 8123100
A32: Francia
A33: Moccassino | B33: =B10*D18 -> 152000 | C33: =C10*D18 -> 160000 | D33: =D10*D18 -> 176000 | E33: 488000 | F33: =F10*D18 -> 190000 | G33: =G10*D18 -> 208000 | H33: =H10*D18 -> 217200 | I33: =SUM(F32:H33) -> 615200 | J33: =J10*E18 -> 234400 | K33: =K10*E18 -> 231200 | L33: =L10*E18 -> 216800 | M33: 682400 | N33: =N10*E18 -> 199200 | O33: =O10*E18 -> 172400 | P33: =P10*E18 -> 154400 | Q33: 526000 | R33: =Q33+M33+I33+E33 -> 2311600
A34: Decollete' | B34: =B11*D19 -> 65000 | C34: =C11*D19 -> 70000 | D34: =D11*D19 -> 90000 | E34: 225000 | F34: =F11*D19 -> 98500 | G34: =G11*D19 -> 117500 | H34: =H11*D19 -> 128000 | I34: =SUM(F34:H34) -> 344000 | J34: =J11*E19 -> 144500 | K34: =K11*E19 -> 150000 | L34: =L11*E19 -> 132000 | M34: 426500 | N34: =N11*E19 -> 110500 | O34: =O11*E19 -> 95000 | P34: =P11*E19 -> 78000 | Q34: =SUM(N34:P34) -> 283500 | R34: =Q34+M34+I34+E34 -> 1279000
A35: Totale | B35: 217000 | C35: 230000 | D35: 266000 | E35: 713000 | F35: =SUM(F33:F34) -> 288500 | G35: =SUM(G33:G34) -> 325500 | H35: =SUM(H33:H34) -> 345200 | I35: =SUM(F35:H35) -> 959200 | J35: 378900 | K35: 381200 | L35: 348800 | M35: =L35+K35+J35 -> 1108900 | N35: =SUM(N33:N34) -> 309700 | O35: =SUM(O33:O34) -> 267400 | P35: =SUM(P33:P34) -> 232400 | Q35: =SUM(Q33:Q34) -> 809500 | R35: =Q35+M35+I35+E35 -> 3590600
A36: TOTALE | B36: =B31+B35 -> 842600 | C36: =C31+C35 -> 810600 | D36: =D31+D35 -> 912200 | E36: =E31+E35 -> 2565400 | F36: =F31+F35 -> 961400 | G36: =G31+G35 -> 1055900 | H36: =H31+H35 -> 1137500 | I36: =I31+I35 -> 3154800 | ... R36: =R31+R35 -> 11713700
A38: BUDGET DEGLI SCONTI
A39: LUREX 1 | B39: GEN. | C39: FEB. | D39: MAR. | E39: I TRIM | F39: APR. | G39: MAG. | H39: GIU. | I39: II TRIM | J39: LUG. | K39: AGO | L39: SET | M39: III TRIM | N39: OTT. | O39: NOV. | P39: DIC. | Q39: IV TRIM. | R39: TOTALE
A40: Italia
A41: Moccassino | B41: =B27*Y5 -> 4800 | C41: 4400 | D41: 4800 | E41: =B41+C41+D41 -> 14000 | F41: =F27*Y5 -> 4800 | G41: =G27*Y5 -> 5200 | H41: =H27*Y5 -> 5600 | I41: =SUM(F41:H41) -> 15600 | J41: =J27*Z5 -> 5440 | K41: =K27*Z5 -> 5080 | L41: =L27*Z5 -> 4960 | M41: =SUM(J41:L41) -> 15480 | N41: =N27*Z5 -> 4688 | O41: =O27*Z5 -> 4336 | P41: =P27*Z5 -> 4000 | Q41: =SUM(N41:P41) -> 13024 | R41: =SUM(Q41+M41+I40+E40) -> 28504
A42: Decollete' | B42: 9000 | C42: 8250 | D42: 9000 | E42: =B42+C42+D42 -> 26250 | F42: =F28*Y6 -> 8700 | G42: =G28*Y6 -> 9150 | H42: =H28*Y6 -> 10095 | I42: =SUM(F42:H42) -> 27945 | J42: =J28*Z6 -> 9840 | K42: =K28*Z6 -> 9150 | L42: =L28*Z6 -> 8940 | M42: =SUM(J42:L42) -> 27930 | N42: =N28*Z6 -> 9000 | O42: =O28*Z6 -> 8610 | P42: =P28*Z6 -> 8070 | Q42: =SUM(N42:P42) -> 25680 | R42: =SUM(Q42+M42+I42+E42) -> 107805
A43: All star | B43: 2400 | C43: 2400 | D43: 3000 | E43: =B43+C43+D43 -> 7800 | F43: =F29*Y7 -> 4020 | G43: =G29*Y7 -> 4632 | H43: =H29*Y7 -> 4920 | I43: =SUM(F43:H43) -> 13572 | J43: =J29*Z7 -> 4680 | K43: =K29*Z7 -> 4860 | L43: =L29*Z7 -> 4560 | M43: =SUM(J43:L43) -> 14100 | N43: =N29*Z7 -> 3780 | O43: =O29*Z7 -> 3468 | P43: =P29*Z7 -> 2544 | Q43: =SUM(N43:P43) -> 9792 | R43: =SUM(Q43+M43+I43+E43) -> 45264
A44: Slip on in pelle | B44: =B30*Y8 -> 768 | C44: =C30*Y8 -> 768 | D44: =D30*Y8 -> 936 | E44: =SUM(B44:D44) -> 2472 | F44: =F30*Y8 -> 1272 | G44: =G30*Y8 -> 1488 | H44: =H30*Y8 -> 1584 | I44: =SUM(F44:H44) -> 4344 | J44: =J30*Z8 -> 1488 | K44: =K30*Z8 -> 1536 | L44: =L30*Z8 -> 1440 | M44: =SUM(J44:L44) -> 4464 | N44: =N30*Z8 -> 1200 | O44: =O30*Z8 -> 1104 | P44: =P30*Z8 -> 1200 | Q44: =SUM(N44:P44) -> 3504 | R44: =SUM(Q44+M44+I44+E44) -> 14784
A45: Totale | B45: =SUM(B41:B44) -> 16968 | C45: =C41+C42+C43+C44 -> 15818 | D45: =D41+D42+D43+D44 -> 17736 | E45: =E41+E42+E43+E44 -> 50522 | F45: =SUM(F41:F44) -> 18792 | G45: =SUM(G41:G44) -> 20470 | H45: =SUM(H41:H44) -> 22199 | I45: =SUM(F45:H45) -> 61461 | J45: 23080.01 | K45: 22330.01 | L45: =SUM(L41:L44) -> 19900 | M45: =SUM(M41:M44) -> 61974 | N45: =SUM(N41:N44) -> 18668 | O45: =SUM(O41:O44) -> 17518 | P45: =SUM(P41:P44) -> 15814 | Q45: =SUM(N45:P45) -> 52000 | R45: =SUM(Q45+M45+I45+E45) -> 225957
A46: Francia
A47: Moccassino | B47: 4560 | C47: 4800 | D47: 5280 | E47: =B47+C47+D47 -> 14640 | F47: =F33*AA5 -> 5700 | G47: =G33*AA5 -> 6240 | H47: =H33*AA5 -> 6516 | I47: =SUM(F47:H47) -> 18456 | J47: =J33*AB5 -> 7032 | K47: =K33*AB5 -> 6936 | L47: =L33*AB5 -> 6504 | M47: =L47+K47+J47 -> 20472 | N47: =N33*AB5 -> 5976 | O47: =O33*AB5 -> 5172 | P47: =P33*AB5 -> 4632 | Q47: =SUM(N47:P47) -> 15780 | R47: =SUM(Q47+M47+I47+E47) -> 69348
A48: Decollete' | B48: 3250 | C48: 3500 | D48: 4500 | E48: =B48+C48+D48 -> 11250 | F48: =F34*AA6 -> 4925 | G48: =G34*AA6 -> 5875 | H48: =H34*AA6 -> 6400 | I48: =SUM(F48:H48) -> 17200 | J48: =J34*AB6 -> 7225 | K48: =K34*AB6 -> 7500 | L48: =L34*AB6 -> 6600 | M48: =J48+K48+L48 -> 21325 | N48: =N34*AB6 -> 5525 | O48: =O34*AB6 -> 4750 | P48: =P34*AB6 -> 3900 | Q48: =SUM(N48:P48) -> 14175 | R48: =SUM(Q48+M48+I48+E48) -> 63950
A49: Totale | B49: 7810 | C49: 8300 | D49: 9780 | E49: =E47+E48 -> 25890 | F49: =SUM(F47:F48) -> 10625 | G49: =SUM(G47:G48) -> 12115 | H49: =SUM(H47:H48) -> 12916 | I49: =SUM(F49:H49) -> 35656 | J49: =J47+J48 -> 14257 | K49: =K47+K48 -> 14436 | L49: =SUM(L47:L48) -> 13104 | M49: =L49+K49+J49 -> 41797 | N49: =SUM(N47:N48) -> 11501 | O49: =SUM(O47:O48) -> 9922 | P49: =SUM(P47:P48) -> 8532 | Q49: =SUM(Q47:Q48) -> 29955 | R49: =Q49+M49+I49+E49 -> 133298
A50: TOTALE | B50: =B45+B49 -> 24778 | C50: =C45+C49 -> 24118 | D50: =D45+D49 -> 27516 | E50: =E45+E49 -> 76412 | F50: =F45+F49 -> 29417 | G50: =G45+G49 -> 32585 | H50: =H45+H49 -> 35115 | I50: =I45+I49 -> 97117 | J50: =J45+J49 -> 37337.01 | K50: =K49+K45 -> 36766.01 | L50: =L45+L49 -> 33004 | M50: =M45+M49 -> 103771 | N50: =N45+N49 -> 30169 | O50: =O45+O49 -> 27440 | P50: =P45+P49 -> 24346 | Q50: =Q45+Q49 -> 81955 | R50: =R45+R49 -> 359255
A51: BUDGET DEL FATTURATO
A52: LUREX 1 | B52: GEN. | C52: FEB. | D52: MAR. | E52: I TRIM | F52: APR. | G52: MAG. | H52: GIU. | I52: II TRIM | J52: LUG. | K52: AGO | L52: SET | M52: III TRIM | N52: OTT. | O52: NOV. | P52: DIC. | Q52: IV TRIM. | R52: TOTALE
A53: Italia
A54: Moccassino | B54: =B27-B41 -> 235200 | C54: =C27-C41 -> 215600 | D54: =D27-D41 -> 235200 | E54: =B54+C54+D54 -> 686000 | F54: =SUM(F27-F41) -> 235200 | G54: =SUM(G27-G41) -> 254800 | H54: =SUM(H27-H41) -> 274400 | I54: =SUM(I27-I41) -> 764400 | J54: =SUM(J27-J41) -> 266560 | K54: =SUM(K27-K41) -> 248920 | L54: =SUM(L27-L41) -> 243040 | M54: =SUM(M27-M41) -> 758520 | ... R54: =SUM(R27-R41) -> 2876696
A55: Decollete' | B55: =B28-B42 -> 291000 | C55: =C28-C42 -> 266750 | D55: =D28-D42 -> 291000 | E55: =B55+C55+D55 -> 848750 | F55: =SUM(F28-F42) -> 281300 | G55: =SUM(G28-G42) -> 295850 | H55: =SUM(H28-H42) -> 326405 | I55: =SUM(I28-I42) -> 903555 | J55: =SUM(J28-J42) -> 318160 | K55: =SUM(K28-K42) -> 295850 | L55: =SUM(L28-L42) -> 289060 | M55: =SUM(M28-M42) -> 903070 | ... R55: =SUM(R28-R42) -> 3485695
A56: All star | B56: =B29-B43 -> 57600 | C56: =C29-C43 -> 57600 | D56: =D29-D43 -> 72000 | E56: =B56+C56+D56 -> 187200 | F56: =SUM(F29-F43) -> 96480 | G56: =SUM(G29-G43) -> 111168 | H56: =SUM(H29-H43) -> 118080 | I56: =SUM(I29-I43) -> 325728 | J56: =SUM(J29-J43) -> 112320 | K56: =SUM(K29-K43) -> 116640 | L56: =SUM(L29-L43) -> 109440 | M56: =SUM(M29-M43) -> 338400 | ... R56: =SUM(R29-R43) -> 1086336
A57: Slip on in pelle | B57: =B30-B44 -> 24832 | C57: =C30-C44 -> 24832 | D57: =D30-D44 -> 30264 | E57: =B57+C57+D57 -> 79928 | F57: =SUM(F30-F44) -> 41128 | G57: =SUM(G30-G44) -> 48112 | H57: =SUM(H30-H44) -> 51216 | I57: =SUM(I30-I44) -> 140456 | J57: =SUM(J30-J44) -> 48112 | K57: =SUM(K30-K44) -> 49664 | L57: =SUM(L30-L44) -> 46560 | M57: =SUM(M30-M44) -> 144336 | ... R57: =SUM(R30-R44) -> 478016
A58: Totale | B58: =B54+B55+B56+B57 -> 608632 | C58: =C54+C55+C56+C57 -> 564782 | D58: =D54+D55+D56+D57 -> 628464 | E58: =B58+C58+D58 -> 1801878 | F58: =SUM(F54:F57) -> 654108 | G58: =SUM(G54:G57) -> 709930 | H58: =SUM(H54:H57) -> 770101 | I58: =SUM(I54:I57) -> 2134139 | J58: =SUM(J54:J57) -> 745152 | K58: =SUM(K54:K57) -> 711074 | L58: =SUM(L54:L57) -> 688100 | M58: =SUM(M54:M57) -> 2144326 | ... R58: =SUM(R54:R57) -> 7926743
A59: Francia
A60: Moccassino | B60: =B33-B47 -> 147440 | C60: =C33-C47 -> 155200 | D60: =D33-D47 -> 170720 | E60: =B60+C60+D60 -> 473360 | F60: =SUM(F33-F47) -> 184300 | G60: =SUM(G33-G47) -> 201760 | H60: =SUM(H33-H47) -> 210684 | I60: =SUM(I33-I47) -> 596744 | J60: =SUM(J33-J47) -> 227368 | K60: =SUM(K33-K47) -> 224264 | L60: =SUM(L33-L47) -> 210296 | M60: =SUM(M33-M47) -> 661928 | ... R60: =SUM(R33-R47) -> 2242252
A61: Decollete' | B61: =B34-B48 -> 61750 | C61: =C34-C48 -> 66500 | D61: =D34-D48 -> 85500 | E61: =B61+C61+D61 -> 213750 | F61: =SUM(F34-F48) -> 93575 | G61: =SUM(G34-G48) -> 111625 | H61: =SUM(H34-H48) -> 121600 | I61: =SUM(I34-I48) -> 326800 | J61: =SUM(J34-J48) -> 137275 | K61: =SUM(K34-K48) -> 142500 | L61: =SUM(L34-L48) -> 125400 | M61: =SUM(M34-M48) -> 405175 | ... R61: =SUM(R34-R48) -> 1215050
A62: Totale | B62: =B60+B61 -> 209190 | C62: =C60+C61 -> 221700 | D62: =D60+D61 -> 256220 | E62: =B62+C62+D62 -> 687110 | F62: =SUM(F60:F61) -> 277875 | G62: =SUM(G60:G61) -> 313385 | H62: =SUM(H60:H61) -> 332284 | I62: =SUM(I60:I61) -> 923544 | J62: =SUM(J60:J61) -> 364643 | K62: =SUM(K60:K61) -> 366764 | L62: =SUM(L60:L61) -> 335696 | M62: =SUM(M60:M61) -> 1067103 | ... Q62: =SUM(Q60:Q61) -> 779545 | R62: =SUM(R35-R49) -> 3457302
A63: TOTALE | B63: =B58+B62 -> 817822 | C63: =C58+C62 -> 786482 | D63: =D58+D62 -> 884684 | E63: =E58+E62 -> 2488988 | F63: =F58+F62 -> 931983 | G63: =G58+G62 -> 1023315 | H63: =H58+H62 -> 1102385 | I63: =I58+I62 -> 3057683 | ... R63: =R58+R62 -> 11384045
A65: BUDGET DELLE PROVVIGIONI ESTERNE
A66: LUREX 1 | B66: GEN. | C66: FEB. | D66: MAR. | E66: I TRIM | F66: APR. | G66: MAG. | H66: GIU. | I66: II TRIM | J66: LUG. | K66: AGO | L66: SET | M66: III TRIM | N66: OTT. | O66: NOV. | P66: DIC. | Q66: IV TRIM. | R66: TOTALE
A67: Italia
A68: Moccassino | B68: =SUM(B5*B18*0.02) -> 4800 | C68: =SUM(C5*B18*0.02) -> 4400 | D68: =D5*B18*0.02 -> 4800 | E68: =SUM(B68:D68) -> 14000 | F68: =SUM(F5*B18*0.02) -> 4800 | G68: =SUM(G5*C18*0.02) -> 5200 | H68: =SUM(H5*C18*0.02) -> 5600 | I68: =SUM(F68:H68) -> 15600 | J68: =SUM(J5*C18*0.02) -> 5440 | K68: =SUM(K5*C18*0.02) -> 5080 | L68: =SUM(L5*C18*0.02) -> 4960 | M68: =SUM(J68:L68) -> 15480 | N68: =SUM(N5*C18*0.02) -> 4688 | O68: =SUM(O5*C18*0.02) -> 4336 | P68: =SUM(P5*C18*0.02) -> 4000 | Q68: =SUM(N68:P68) -> 13024 | R68: =SUM(E68+I68+M68+Q68) -> 58104
A69: Decollete' | B69: =SUM(B6*B19*0.02) -> 6000 | C69: =SUM(C6*B19*0.02) -> 5500 | D69: =SUM(D6*B19*0.02) -> 6000 | E69: =SUM(B69:D69) -> 17500 | F69: =SUM(F6*B19*0.02) -> 5800 | G69: =SUM(G6*C19*0.02) -> 6100 | H69: =SUM(H6*C19*0.02) -> 6730 | I69: =SUM(F69:H69) -> 18630 | J69: =SUM(J6*C19*0.02) -> 6560 | K69: =SUM(K6*C19*0.02) -> 6100 | L69: =SUM(L6*C19*0.02) -> 5960 | M69: =SUM(J69:L69) -> 18620 | N69: =SUM(N6*C19*0.02) -> 6000 | O69: =SUM(O6*C19*0.02) -> 5740 | P69: =SUM(P6*C19*0.02) -> 5380 | Q69: =SUM(N69:P69) -> 17120 | R69: =SUM(E69+I69+M69+Q69) -> 71870
A70: All star | B70: =SUM(B7*B20*0.02) -> 1200 | C70: =SUM(C7*B20*0.02) -> 1200 | D70: =SUM(D7*B20*0.02) -> 1500 | E70: =SUM(B70:D70) -> 3900 | F70: =SUM(F7*B20*0.02) -> 2010 | G70: =SUM(G7*C20*0.02) -> 2316 | H70: =SUM(H7*C20*0.02) -> 2460 | I70: =SUM(F70:H70) -> 6786 | J70: =SUM(J7*C20*0.02) -> 2340 | K70: =SUM(K7*C20*0.02) -> 2430 | L70: =SUM(L7*C20*0.02) -> 2280 | M70: =SUM(J70:L70) -> 7050 | N70: =SUM(N7*C20*0.02) -> 1890 | O70: =SUM(O7*C20*0.02) -> 1734 | P70: =SUM(P7*C20*0.02) -> 1272 | Q70: =SUM(N70:P70) -> 4896 | R70: =SUM(E70+I70+M70+Q70) -> 22632
A71: Slip on in pelle | B71: =SUM(B8*B21*Y22) -> 512 | C71: =SUM(C8*B21*Y22) -> 512 | D71: =SUM(D8*B21*Y22) -> 624 | E71: =SUM(B71:D71) -> 1648 | F71: =SUM(F8*B21*Y22) -> 848 | G71: =SUM(G8*B21*Y22) -> 992 | H71: =SUM(H8*B21*Y22) -> 1056 | I71: =SUM(F71:H71) -> 2896 | J71: =SUM(J8*C21*Z22) -> 992 | K71: =SUM(K8*C21*Z22) -> 1024 | L71: =SUM(L8*C21*Z22) -> 960 | M71: =SUM(J71:L71) -> 2976 | N71: =SUM(N8*C21*Z22) -> 800 | O71: =SUM(O8*C21*Z22) -> 736 | P71: =SUM(P8*C21*Z22) -> 800 | Q71: =SUM(N71:P71) -> 2336 | R71: =SUM(E71+I71+M71+Q71) -> 9856
A72: Totale | B72: =SUM(B68:B71) -> 12512 | C72: =SUM(C68:C71) -> 11612 | D72: =SUM(D68:D71) -> 12924 | E72: =SUM(E68:E71) -> 37048 | F72: =SUM(F68:F71) -> 13458 | G72: =SUM(G68:G71) -> 14608 | H72: =SUM(H68:H71) -> 15846 | I72: =SUM(I68:I71) -> 43912 | ... R72: =SUM(R68:R71) -> 162462
A73: Francia
A74: Moccassino | B74: =SUM(B10*D18*0.03) -> 4560 | C74: =SUM(C10*D19*0.03) -> 6000 | D74: =SUM(D10*D18*0.03) -> 5280 | E74: =SUM(B74:D74) -> 15840 | F74: =SUM(F10*D18*0.03) -> 5700 | G74: =SUM(G10*D18*0.03) -> 6240 | H74: =SUM(H10*D18*0.03) -> 6516 | I74: =SUM(F74:H74) -> 18456 | J74: =SUM(J10*E18*0.03) -> 7032 | K74: =SUM(K10*E18*0.03) -> 6936 | L74: =SUM(L10*E18*0.03) -> 6504 | M74: =SUM(J74:L74) -> 20472 | N74: =SUM(N10*E18*0.03) -> 5976 | O74: =SUM(O10*E18*0.03) -> 5172 | P74: =SUM(P10*E18*0.03) -> 4632 | Q74: =SUM(N74:P74) -> 15780 | R74: =SUM(E74+I74+M74+Q74) -> 70548
A75: Decollete' | B75: =SUM(B11*D19*0.03) -> 1950 | C75: =SUM(C11*D19*0.03) -> 2100 | D75: =SUM(D11*D19*0.03) -> 2700 | E75: =SUM(A75:D75) -> 6750 | F75: =SUM(F11*D19*0.03) -> 2955 | G75: =SUM(G11*D19*0.03) -> 3525 | H75: =SUM(H11*D19*0.03) -> 3840 | I75: =SUM(F75:H75) -> 10320 | J75: =SUM(J11*E19*0.03) -> 4335 | K75: =SUM(K11*E19*0.03) -> 4500 | L75: =SUM(L11*E19*0.03) -> 3960 | M75: =SUM(J75:L75) -> 12795 | N75: =SUM(N11*E19*0.03) -> 3315 | O75: =SUM(O11*E19*0.03) -> 2850 | P75: =SUM(P11*E19*0.03) -> 2340 | Q75: =SUM(N75:P75) -> 8505 | R75: =SUM(E75+I75+M75+Q75) -> 38370
A76: Totale | B76: =SUM(B74:B75) -> 6510 | C76: =SUM(C74:C75) -> 8100 | D76: =SUM(D74:D75) -> 7980 | E76: =SUM(E74:E75) -> 22590 | F76: =SUM(F74:F75) -> 8655 | G76: =SUM(G74:G75) -> 9765 | H76: =SUM(H74:H75) -> 10356 | I76: =SUM(I74:I75) -> 28776 | ... R76: =SUM(R74:R75) -> 108918
A77: TOTALE | B77: =B72+B76 -> 19022 | C77: =C72+C76 -> 19712 | D77: =D72+D76 -> 20904 | E77: =E72+E76 -> 59638 | F77: =F72+F76 -> 22113 | G77: =G72+G76 -> 24373 | H77: =H72+H76 -> 26202 | I77: =I72+I76 -> 72688 | ... Q77: =Q72+Q76 -> 61661 | R77: =Q76+M77+I77+E77 -> 234004
A79: BUDGET DEI COSTI DI TRASPORTO
A80: LUREX 1 | B80: GEN. | C80: FEB. | D80: MAR. | E80: I TRIM | F80: APR. | G80: MAG. | H80: GIU. | I80: II TRIM | J80: LUG. | K80: AGO | L80: SET | M80: III TRIM | N80: OTT. | O80: NOV. | P80: DIC. | Q80: IV TRIM. | R80: TOTALE
A81: Italia
A82: Moccassino | B82: =B5*Y12 -> 1800 | C82: =C5*Y12 -> 1650 | D82: =D5*Y12 -> 1800 | E82: =SUM(B82:D82) -> 5250 | F82: =F5*Y12 -> 1800 | G82: =G5*Y12 -> 1950 | H82: =H5*Y12 -> 2100 | I82: =SUM(F82:H82) -> 5850 | J82: =J5*Z12 -> 2380 | K82: =K5*Z12 -> 2222.5 | L82: =L5*Z12 -> 2170 | M82: =SUM(J82:L82) -> 6772.5 | N82: =N5*Z12 -> 2051 | O82: =O5*Z12 -> 1897 | P82: =P5*Z12 -> 1750 | Q82: =SUM(N82:P82) -> 5698 | R82: =SUM(E82+I82+M82+Q82) -> 23570.5
A83: Decollete' | B83: =B6*Y13 -> 1800 | C83: =C6*Y13 -> 1650 | D83: =D6*Y13 -> 1800 | E83: =SUM(B83:D83) -> 5250 | F83: =F6*Y13 -> 1740 | G83: =G6*Y13 -> 1830 | H83: =H6*Y13 -> 2019 | I83: =SUM(F83:H83) -> 5589 | J83: =J6*Z13 -> 2296 | K83: =K6*Z13 -> 2135 | L83: =L6*Z13 -> 2086 | M83: =SUM(J83:L83) -> 6517 | N83: =N6*Z13 -> 2100 | O83: =O6*Z13 -> 2009 | P83: =P6*Z13 -> 1883 | Q83: =SUM(N83:P83) -> 5992 | R83: =SUM(E83+I83+M83+Q83) -> 23348
A84: All star | B84: =B7*Y14 -> 600 | C84: =C7*Y14 -> 600 | D84: =D7*Y14 -> 750 | E84: =SUM(B84:D84) -> 1950 | F84: =F7*Y14 -> 1005 | G84: =G7*Y14 -> 1158 | H84: =H7*Y14 -> 1230 | I84: =SUM(F84:H84) -> 3393 | J84: =J7*Z14 -> 1365 | K84: =K7*Z14 -> 1417.5 | L84: =L7*Z14 -> 1330 | M84: =SUM(J84:L84) -> 4112.5 | N84: =N7*Z14 -> 1102.5 | O84: =O7*Z14 -> 1011.5 | P84: =P7*Z14 -> 742 | Q84: =SUM(N84:P84) -> 2856 | R84: =SUM(E84+I84+M84+Q84) -> 12311.5
A85: Slip on in pelle | B85: =B8*Y15 -> 192 | C85: =C8*Y15 -> 192 | D85: =D8*Y15 -> 234 | E85: =SUM(B85:D85) -> 618 | F85: =F8*Y15 -> 318 | G85: =G8*Y15 -> 372 | H85: =H8*Y15 -> 396 | I85: =SUM(F85:H85) -> 1086 | J85: =J8*Z15 -> 372 | K85: =K8*Z15 -> 384 | L85: =L8*Z15 -> 360 | M85: =SUM(J85:L85) -> 1116 | N85: =N8*Z15 -> 300 | O85: =O8*Z15 -> 276 | P85: =P8*Z15 -> 300 | Q85: =SUM(N85:P85) -> 876 | R85: =SUM(E85+I85+M85+Q85) -> 3696
A86: Totale | B86: =SUM(B82:B85) -> 4392 | C86: =SUM(C82:C85) -> 4092 | D86: =SUM(D82:D85) -> 4584 | E86: =SUM(E82:E85) -> 13068 | F86: =SUM(F82:F85) -> 4863 | G86: =SUM(G82:G85) -> 5310 | H86: =SUM(H82:H85) -> 5745 | I86: =SUM(I82:I85) -> 15918 | ... R86: =SUM(R82:R85) -> 62926
A87: Francia
A88: Moccassino | B88: =B10*AA12 -> 1900 | C88: =C10*AA12 -> 2000 | D88: =D10*AA12 -> 2200 | E88: =SUM(B88:D88) -> 6100 | F88: =F10*AA12 -> 2375 | G88: =G10*AA12 -> 2600 | H88: =H10*AA12 -> 2715 | I88: =SUM(F88:H88) -> 7690 | J88: =J10*AB12 -> 3223 | K88: =K10*AB12 -> 3179 | L88: =L10*AB12 -> 2981 | M88: =SUM(J88:L88) -> 9383 | N88: =N10*AB12 -> 2739 | O88: =O10*AB12 -> 2370.5 | P88: =P10*AB12 -> 2123 | Q88: =SUM(N88:P88) -> 7232.5 | R88: =SUM(E88+I88+M88+Q88) -> 30405.5
A89: Decollete' | B89: =B11*AA13 -> 650 | C89: =C11*AA13 -> 700 | D89: =D11*AA13 -> 900 | E89: =SUM(B89:D89) -> 2250 | F89: =F11*AA13 -> 985 | G89: =G11*AA13 -> 1175 | H89: =H11*AA13 -> 1280 | I89: =SUM(F89:H89) -> 3440 | J89: =J11*AB13 -> 1589.5 | K89: =J11*AB13 -> 1589.5 | L89: =L11*AB13 -> 1452 | M89: =SUM(J89:L89) -> 4631 | N89: =N11*AB13 -> 1215.5 | O89: =O11*AB13 -> 1045 | P89: =P11*AB13 -> 858 | Q89: =SUM(N89:P89) -> 3118.5 | R89: =SUM(E89+I89+M89+Q89) -> 13439.5
A90: Totale | B90: =SUM(B88:B89) -> 2550 | C90: =SUM(C88:C89) -> 2700 | D90: =SUM(D88:D89) -> 3100 | E90: =SUM(E88:E89) -> 8350 | F90: =SUM(F88:F89) -> 3360 | G90: =SUM(G88:G89) -> 3775 | H90: =SUM(H88:H89) -> 3995 | I90: =SUM(I88:I89) -> 11130 | ... R90: =SUM(R88:R89) -> 43845
A91: TOTALE | B91: =B86+B90 -> 6942 | C91: =C86+C90 -> 6792 | D91: =D86+D90 -> 7684 | E91: =E86+E90 -> 21418 | F91: =F86+F90 -> 8223 | G91: =G86+G90 -> 9085 | H91: =H86+H90 -> 9740 | I91: =I86+I90 -> 27048 | ... R91: =R86+R90 -> 106771
A93: BUDGET MARGINE COMMERCIALE MOCCASSINO
A95: LUREX 1 | B95: GEN. | C95: FEB. | D95: MAR. | E95: I TRIM | F95: APR. | G95: MAG. | H95: GIU. | I95: II TRIM | J95: LUG. | K95: AGO | L95: SET | M95: III TRIM | N95: OTT. | O95: NOV. | P95: DIC. | Q95: IV TRIM. | R95: TOTALE
A96: Ricavi di Vendita | B96: =B27+B33 -> 392000 | C96: =C27+C33 -> 380000 | D96: =D27+D33 -> 416000 | E96: =E27+E33 -> 1188000 | F96: =F27+F33 -> 430000 | G96: =G27+G33 -> 468000 | H96: =H27+H33 -> 497200 | I96: =I27+I33 -> 1395200 | ... R96: =R27+R33 -> 5216800
A97: - Sconti | B97: =B41+B47 -> 9360 | C97: =C41+C47 -> 9200 | D97: =D41+D47 -> 10080 | E97: =SUM(B97:D97) -> 28640 | F97: =F41+F47 -> 10500 | G97: =G41+G47 -> 11440 | H97: =H41+H47 -> 12116 | I97: =F97+G97+H97 -> 34056 | J97: =J41+J47 -> 12472 | K97: =K41+K47 -> 12016 | L97: =L41+L47 -> 11464 | M97: =J97+K97+L97 -> 35952 | N97: =N41+N47 -> 10664 | O97: =O41+O47 -> 9508 | P97: =P41+P47 -> 8632 | Q97: =SUM(N97:P97) -> 28804 | R97: =E97+I97+M97+Q97 -> 127452
A98: Fatturato | B98: ='BUDGET PRODUZIONE'!B442-B97 -> 382640 | C98: ='BUDGET PRODUZIONE'!C442-C97 -> 370800 | D98: ='BUDGET PRODUZIONE'!D442-D97 -> 405920 | E98: =SUM(B98:D98) -> 1159360 | F98: ='BUDGET PRODUZIONE'!F442-F97 -> 419500 | G98: ='BUDGET PRODUZIONE'!G442-G97 -> 456560 | H98: ='BUDGET PRODUZIONE'!H442-H97 -> 485084 | I98: ='BUDGET PRODUZIONE'!I442-I97 -> 1361144 | J98: ='BUDGET PRODUZIONE'!J442-J97 -> 493928 | K98: ='BUDGET PRODUZIONE'!K442-K97 -> 473184 | L98: ='BUDGET PRODUZIONE'!L442+L97 -> 476264 | M98: ='BUDGET PRODUZIONE'!M442-M97 -> 1420448 | N98: ='BUDGET PRODUZIONE'!N442-N97 -> 422936 | O98: ='BUDGET PRODUZIONE'!O442+O97 -> 398708 | P98: ='BUDGET PRODUZIONE'!P442+P97 -> 363032 | Q98: ='BUDGET PRODUZIONE'!Q442-Q97 -> 1148396 | R98: =E98+I98+M98+Q98 -> 5089348
A99: - Costi di Trasporto | B99: =B82+B88 -> 3700 | C99: =C82+C88 -> 3650 | D99: =D82+D88 -> 4000 | E99: =SUM(B99:D99) -> 11350 | F99: =F82+F88 -> 4175 | G99: =G82+G88 -> 4550 | H99: =H82+H88 -> 4815 | I99: =SUM(F99:H99) -> 13540 | J99: =J82+J88 -> 5603 | K99: =K82+K88 -> 5401.5 | L99: =L82+L88 -> 5151 | M99: =J99+K99+L99 -> 16155.5 | N99: =N82+N88 -> 4790 | O99: =O82+O88 -> 4267.5 | P99: =P82+P88 -> 3873 | Q99: =SUM(N99:P99) -> 12930.5 | R99: =SUM(Q99+E99+I99+M99) -> 53976
A100: - Provvigioni esterne | B100: =B68+B74 -> 9360 | C100: =C68+C74 -> 10400 | D100: =D68+D74 -> 10080 | E100: =SUM(B100:D100) -> 29840 | F100: =SUM(F68+F74) -> 10500 | G100: =G74+G68 -> 11440 | H100: =H74+H68 -> 12116 | I100: =SUM(F100:H100) -> 34056 | J100: =J68+J74 -> 12472 | K100: =K68+K74 -> 12016 | L100: =L68+L74 -> 11464 | M100: =SUM(J100:L100) -> 35952 | N100: =N68+N74 -> 10664 | O100: =SUM(O68+O74) -> 9508 | P100: =P68+P74 -> 8632 | Q100: =SUM(N100:P100) -> 28804 | R100: =Q100+M100+I100+E100 -> 128652
A101: Margine contribuzione comm. | B101: =B98-(B99+B100) -> 369580 | C101: =C98-(C99+C100) -> 356750 | D101: =D98-D99-D100 -> 391840 | E101: =E98-E99-E100 -> 1118170 | F101: =F98-F99-F100 -> 404825 | G101: =G98-G99-G100 -> 440570 | H101: =H98-H99-H100 -> 468153 | I101: =I98-I99-I100 -> 1313548 | J101: =J98-J99-J100 -> 475853 | K101: =K98-K99-K100 -> 455766.5 | L101: =L98-L99-L100 -> 459649 | M101: =J101+K101+L101 -> 1391268.5 | N101: =N98-(N99+N100) -> 407482 | O101: =O98-(O99+O100) -> 384932.5 | P101: =P98-(P99+P100) -> 350527 | Q101: =Q98-(Q99+Q100) -> 1106661.5 | R101: =E101+I101+M101+Q101 -> 4929648
A104: BUDGET MARGINE COMMERCIALE DECOLLETE'
A106: LUREX 1 | B106: GEN. | C106: FEB. | D106: MAR. | E106: I TRIM | F106: APR. | G106: MAG. | H106: GIU. | I106: II TRIM | J106: LUG. | K106: AGO | L106: SET | M106: III TRIM | N106: OTT. | O106: NOV. | P106: DIC. | Q106: IV TRIM. | R106: TOTALE
A107: Ricavi di Vendita | B107: =B27+B33 -> 392000 | C107: =C27+C33 -> 380000 | D107: =D27+D33 -> 416000 | E107: =B107+C107+D107 -> 1188000 | F107: =F27+F33 -> 430000 | G107: =G27+G33 -> 468000 | H107: =H27+H33 -> 497200 | I107: =F107+G107+H107 -> 1395200 | J107: =J27+J33 -> 506400 | K107: =K27+K33 -> 485200 | L107: =L27+L33 -> 464800 | M107: =J107+K107+L107 -> 1456400 | N107: =N27+N33 -> 433600 | O107: =O27+O33 -> 389200 | P107: =P27+P33 -> 354400 | Q107: =N107+O107+P107 -> 1177200 | R107: =E107+I107+M107+Q107 -> 5216800
A108: - Sconti | B108: =B41+B47 -> 9360 | C108: =C41+C47 -> 9200 | D108: =D47+D41 -> 10080 | E108: =B108+C108+D108 -> 28640 | F108: =F41+F47 -> 10500 | G108: =G41+G47 -> 11440 | H108: =H41+H47 -> 12116 | I108: =F108+G108+H108 -> 34056 | J108: =J41+J47 -> 12472 | K108: =K41+K47 -> 12016 | L108: =L41+L47 -> 11464 | M108: =J108+K108+L108 -> 35952 | N108: =N41+N47 -> 10664 | O108: =O41+O47 -> 9508 | P108: =P41+P47 -> 8632 | Q108: =N108+O108+P108 -> 28804 | R108: =E108+I108+M108+Q108 -> 127452
A109: Fatturato | B109: =B107-B108 -> 382640 | C109: =C107-C108 -> 370800 | D109: =D107-D108 -> 405920 | E109: =B109+C109+D109 -> 1159360 | F109: =F107+F108 -> 440500 | G109: =G107+G108 -> 479440 | H109: =H107+H108 -> 509316 | I109: =F109+G109+H109 -> 1429256 | J109: =J107+J108 -> 518872 | K109: =K107+K108 -> 497216 | L109: =L107+L108 -> 476264 | M109: =J109+K109+L109 -> 1492352 | N109: =N107+N108 -> 444264 | O109: =O107+O108 -> 398708 | P109: =P107+P108 -> 363032 | Q109: =N109+O109+P109 -> 1206004 | R109: =E109+I109+M109+Q109 -> 5286972
...

Sheet BUDGET PRODUZIONE
A1: Budget della produzione | T1: Distinta base della produzione
A3: Piano integrato di produzione, vendita e scorte di prodotti finiti | T3: LUREX 1 | U3: Centri Produttivi | V3: centri produttivi
A4: LUREX 1 | B4: GEN. | C4: FEB. | D4: MAR. | E4: I TRIM | F4: APR. | G4: MAG. | H4: GIU. | I4: II TRIM | J4: LUG. | K4: AGO. | L4: SET. | M4: III TRIM | N4: OTT. | O4: NOV. | P4: DIC. | Q4: IV TRIM | R4: Riepilogo Annuale | V4: Centro 1-taglio | W4: Centro 2-aggiunteria | X4: Centro 3-Montaggio | Y4: Centro 4-rifinitura e confezionamento
T5: Linea classica Mocassino | U5: Tempo Uomo | V5: 0.08 | W5: 0.42 | X5: 0.08 | Y5: 0.12
A6: Rimanenze Iniziali | U6: Tempo Macchina | V6: 0.08 | W6: 0.42 | X6: 0.01 | Y6: 0.08
A7: Mocassino | B7: 1 | C7: =B17 -> 950 | D7: =C17 -> 1040 | E7: =SUM(B7:D7) -> 1991 | F7: =D17 -> 1075 | G7: =F17 -> 1170 | H7: =G17 -> 1864.5 | I7: =SUM(F7:H7) -> 4109.5 | J7: =H17 -> 1899 | K7: =J17 -> 1819.5 | L7: =K17 -> 1743 | M7: =SUM(J7:L7) -> 5461.5 | N7: =L17 -> 1626 | O7: =N17 -> 1459.5 | P7: =O17 -> 886 | Q7: =SUM(N7:P7) -> 3971.5 | R7: =SUM(E7+I7+M7+Q7) -> 15533.5 | U7: scarto | V7: 0.02 | W7: 0 | X7: 0 | Y7: 0
A8: Decollete' | B8: 1 | C8: =B18 -> 345 | D8: =C18 -> 390 | E8: =SUM(B8:D8) -> 736 | F8: =D18 -> 777 | G8: =F18 -> 1690 | H8: =G18 -> 1858 | I8: =SUM(F8:H8) -> 4325 | J8: =H18 -> 1890 | K8: =J18 -> 1820 | L8: =K18 -> 860 | M8: =SUM(J8:L8) -> 4570 | N8: =L18 -> 821 | O8: =N18 -> 382 | P8: =O18 -> 347 | Q8: =SUM(N8:P8) -> 1550 | R8: =SUM(E8+I8+M8+Q8) -> 11181 | U8: pelle | V8: 0.3 | W8: 0 | X8: 0 | Y8: 0
A9: All Star | B9: 1 | C9: =B19 -> 200 | D9: =C19 -> 250 | E9: =SUM(B9:D9) -> 451 | F9: =D19 -> 335 | G9: =F19 -> 193 | H9: =G19 -> 205 | I9: =SUM(F9:H9) -> 733 | J9: =H19 -> 195 | K9: =J19 -> 202.5 | L9: =K19 -> 190 | M9: =SUM(J9:L9) -> 587.5 | N9: =L19 -> 157.5 | O9: =N19 -> 144.5 | P9: =O19 -> 106 | Q9: =SUM(N9:P9) -> 408 | R9: =SUM(E9+I9+M9+Q9) -> 2179.5 | U9: filo | V9: 0 | W9: 8 | X9: 0 | Y9: 0
A10: Slip on in pelle | B10: 0 | C10: =B20 -> 32 | D10: =C20 -> 39 | E10: =SUM(B10:D10) -> 71 | F10: =D20 -> 53 | G10: =F20 -> 12.4 | H10: =G20 -> 198 | I10: =SUM(F10:H10) -> 263.4 | J10: =H20 -> 186 | K10: =J20 -> 192 | L10: =K20 -> 180 | M10: =SUM(J10:L10) -> 558 | N10: =L20 -> 100 | O10: =N20 -> 92 | P10: =O20 -> 50 | Q10: =SUM(N10:P10) -> 242 | R10: =SUM(E10+I10+M10+Q10) -> 1134.4 | U10: suole | V10: 0 | W10: 0 | X10: 1 | Y10: 0
A11: Vendite
A12: Mocassino | B12: ='BUDGET COMMERCIALE'!B5+'BUDGET COMMERCIALE'!B10 -> 9800 | C12: ='BUDGET COMMERCIALE'!C5+'BUDGET COMMERCIALE'!C10 -> 9500 | D12: ='BUDGET COMMERCIALE'!D5+'BUDGET COMMERCIALE'!D10 -> 10400 | E12: =SUM('BUDGET PRODUZIONE'!B12:D12) -> 29700 | F12: ='BUDGET COMMERCIALE'!F5+'BUDGET COMMERCIALE'!F10 -> 10750 | G12: ='BUDGET COMMERCIALE'!G5+'BUDGET COMMERCIALE'!G10 -> 11700 | H12: ='BUDGET COMMERCIALE'!H5+'BUDGET COMMERCIALE'!H10 -> 12430 | I12: =SUM(F12:H12) -> 34880 | J12: ='BUDGET COMMERCIALE'!J5+'BUDGET COMMERCIALE'!J10 -> 12660 | K12: ='BUDGET COMMERCIALE'!K5+'BUDGET COMMERCIALE'!K10 -> 12130 | L12: ='BUDGET COMMERCIALE'!L5+'BUDGET COMMERCIALE'!L10 -> 11620 | M12: =SUM(J12:L12) -> 36410 | N12: ='BUDGET COMMERCIALE'!N5+'BUDGET COMMERCIALE'!N10 -> 10840 | O12: ='BUDGET COMMERCIALE'!O5+'BUDGET COMMERCIALE'!O10 -> 9730 | P12: ='BUDGET COMMERCIALE'!P5+'BUDGET COMMERCIALE'!P10 -> 8860 | Q12: =SUM(N12:P12) -> 29430 | R12: =SUM(E12+I12+M12+Q12) -> 130420
A13: Decollete' | B13: ='BUDGET COMMERCIALE'!B6+'BUDGET COMMERCIALE'!B11 -> 7300 | C13: ='BUDGET COMMERCIALE'!C6+'BUDGET COMMERCIALE'!C11 -> 6900 | D13: ='BUDGET COMMERCIALE'!D6+'BUDGET COMMERCIALE'!D11 -> 7800 | E13: =SUM(B13:D13) -> 22000 | F13: ='BUDGET COMMERCIALE'!F6+'BUDGET COMMERCIALE'!F11 -> 7770 | G13: ='BUDGET COMMERCIALE'!G6+'BUDGET COMMERCIALE'!G11 -> 8450 | H13: ='BUDGET COMMERCIALE'!H6+'BUDGET COMMERCIALE'!H11 -> 9290 | I13: =SUM(F13:H13) -> 25510 | J13: ='BUDGET COMMERCIALE'!J6+'BUDGET COMMERCIALE'!J11 -> 9450 | K13: ='BUDGET COMMERCIALE'!K6+'BUDGET COMMERCIALE'!K11 -> 9100 | L13: ='BUDGET COMMERCIALE'!L6+'BUDGET COMMERCIALE'!L11 -> 8600 | M13: =SUM(J13:L13) -> 27150 | N13: ='BUDGET COMMERCIALE'!N6+'BUDGET COMMERCIALE'!N11 -> 8210 | O13: ='BUDGET COMMERCIALE'!O6+'BUDGET COMMERCIALE'!O11 -> 7640 | P13: ='BUDGET COMMERCIALE'!P6+'BUDGET COMMERCIALE'!P11 -> 6940 | Q13: =SUM(N13:P13) -> 22790 | R13: =SUM(E13+I13+M13+Q13) -> 97450 | T13: Linea classica decollete' | U13: Tempo Uomo | V13: 0.08 | W13: 0.33 | X13: 0.08 | Y13: 0.12
A14: All Star | B14: ='BUDGET COMMERCIALE'!B7 -> 2000 | C14: ='BUDGET COMMERCIALE'!C7 -> 2000 | D14: ='BUDGET COMMERCIALE'!D7 -> 2500 | E14: =SUM(B14:D14) -> 6500 | F14: ='BUDGET COMMERCIALE'!F7 -> 3350 | G14: ='BUDGET COMMERCIALE'!G7 -> 3860 | H14: ='BUDGET COMMERCIALE'!H7 -> 4100 | I14: =SUM(F14:H14) -> 11310 | J14: ='BUDGET COMMERCIALE'!J7 -> 3900 | K14: ='BUDGET COMMERCIALE'!K7 -> 4050 | L14: ='BUDGET COMMERCIALE'!L7 -> 3800 | M14: =SUM(J14:L14) -> 11750 | N14: ='BUDGET COMMERCIALE'!N7 -> 3150 | O14: ='BUDGET COMMERCIALE'!O7 -> 2890 | P14: ='BUDGET COMMERCIALE'!P7 -> 2120 | Q14: =SUM(N14:P14) -> 8160 | R14: =SUM(E14+I14+M14+Q14) -> 37720 | U14: Tempo Macchina | V14: 0.08 | W14: 0.33 | X14: 0.01 | Y14: 0.08
A15: Slip on in pelle | B15: ='BUDGET COMMERCIALE'!B8 -> 640 | C15: ='BUDGET COMMERCIALE'!C8 -> 640 | D15: ='BUDGET COMMERCIALE'!D8 -> 780 | E15: =SUM(B15:D15) -> 2060 | F15: ='BUDGET COMMERCIALE'!F8 -> 1060 | G15: ='BUDGET COMMERCIALE'!G8 -> 1240 | H15: ='BUDGET COMMERCIALE'!H8 -> 1320 | I15: =SUM(F15:H15) -> 3620 | J15: ='BUDGET COMMERCIALE'!J8 -> 1240 | K15: ='BUDGET COMMERCIALE'!K8 -> 1280 | L15: ='BUDGET COMMERCIALE'!L8 -> 1200 | M15: =SUM(J15:L15) -> 3720 | N15: ='BUDGET COMMERCIALE'!N8 -> 1000 | O15: ='BUDGET COMMERCIALE'!O8 -> 920 | P15: ='BUDGET COMMERCIALE'!P8 -> 1000 | Q15: =SUM(N15:P15) -> 2920 | R15: =SUM(E15+I15+M15+Q15) -> 12320 | U15: scarto | V15: 0.01 | W15: 0 | X15: 0 | Y15: 0
A16: Rimanenze Finali programmate | U16: pelle | V16: 0.25 | W16: 0 | X16: 0 | Y16: 0
A17: Mocassino | B17: =C12*0.1 -> 950 | C17: =D12*0.1 -> 1040 | D17: =F12*0.1 -> 1075 | E17: =SUM(B17:D17) -> 3065 | F17: =G12*0.1 -> 1170 | G17: =H12*0.15 -> 1864.5 | H17: =J12*0.15 -> 1899 | I17: =SUM(F17:H17) -> 4933.5 | J17: =K12*0.15 -> 1819.5 | K17: =L12*0.15 -> 1743 | L17: =N12*0.15 -> 1626 | M17: =SUM(J17:L17) -> 5188.5 | N17: =O12*0.15 -> 1459.5 | O17: =P12*0.1 -> 886 | P17: =B12*0.1 -> 980 | Q17: =SUM(N17:P17) -> 3325.5 | R17: =SUM(E17+I17+M17+Q17) -> 16512.5 | U17: filo | V17: 0 | W17: 7 | X17: 0 | Y17: 0
A18: Decollete' | B18: =C13*0.05 -> 345 | C18: =D13*0.05 -> 390 | D18: =F13*0.1 -> 777 | E18: =SUM(B18:D18) -> 1512 | F18: =G13*0.2 -> 1690 | G18: =H13*0.2 -> 1858 | H18: =J13*0.2 -> 1890 | I18: =SUM(F18:H18) -> 5438 | J18: =K13*0.2 -> 1820 | K18: =L13*0.1 -> 860 | L18: =N13*0.1 -> 821 | M18: =SUM(J18:L18) -> 3501 | N18: =O13*0.05 -> 382 | O18: =P13*0.05 -> 347 | P18: =B13*0.05 -> 365 | Q18: =SUM(N18:P18) -> 1094 | R18: =SUM(E18+I18+M18+Q18) -> 11545 | U18: suole | V18: 0 | W18: 0 | X18: 1 | Y18: 0
A19: All Star | B19: =C14*0.1 -> 200 | C19: =D14*0.1 -> 250 | D19: =F14*0.1 -> 335 | E19: =SUM(B19:D19) -> 785 | F19: =G14*0.05 -> 193 | G19: =H14*0.05 -> 205 | H19: =J14*0.05 -> 195 | I19: =SUM(F19:H19) -> 593 | J19: =K14*0.05 -> 202.5 | K19: =L14*0.05 -> 190 | L19: =N14*0.05 -> 157.5 | M19: =SUM(J19:L19) -> 550 | N19: =O14*0.05 -> 144.5 | O19: =P14*0.05 -> 106 | P19: =B14*0.05 -> 100 | Q19: =SUM(N19:P19) -> 350.5 | R19: =SUM(E19+I19+M19+Q19) -> 2278.5
A20: Slip on in pelle | B20: =C15*0.05 -> 32 | C20: =D15*0.05 -> 39 | D20: =F15*0.05 -> 53 | E20: =SUM(B20:D20) -> 124 | F20: =G15*0.01 -> 12.4 | G20: =H15*0.15 -> 198 | H20: =J15*0.15 -> 186 | I20: =SUM(F20:H20) -> 396.4 | J20: =K15*0.15 -> 192 | K20: =L15*0.15 -> 180 | L20: =N15*0.1 -> 100 | M20: =SUM(J20:L20) -> 472 | N20: =O15*0.1 -> 92 | O20: =P15*0.05 -> 50 | P20: =B15*0.05 -> 32 | Q20: =SUM(N20:P20) -> 174 | R20: =SUM(E20+I20+M20+Q20) -> 1166.4
A21: Rimanenze Finali Effettive | T21: Linea sportiva All Star | U21: Tempo Uomo | V21: 0.08 | W21: 0.41 | X21: 0.05 | Y21: 0.12
A22: Mocassino | B22: =SUM(B17) -> 950 | C22: =SUM(C17) -> 1040 | D22: =SUM(D17) -> 1075 | E22: =SUM(E17) -> 3065 | F22: =SUM(F17) -> 1170 | G22: =SUM(G17) -> 1864.5 | H22: =SUM(H17) -> 1899 | I22: =SUM(I17) -> 4933.5 | ... R22: =SUM(R17) -> 16512.5 | U22: Tempo Macchina | V22: 0.08 | W22: 0.41 | X22: 0.01 | Y22: 0.08
A23: Decollete' | B23: =SUM(B18) -> 345 | C23: =SUM(C18) -> 390 | D23: =SUM(D18) -> 777 | E23: =SUM(E18) -> 1512 | F23: =SUM(F18) -> 1690 | G23: =SUM(G18) -> 1858 | H23: =SUM(H18) -> 1890 | I23: =SUM(I18) -> 5438 | ... R23: =SUM(R18) -> 11545 | U23: scarto | V23: 0.01 | W23: 0 | X23: 0 | Y23: 0
A24: All Star | B24: =SUM(B19) -> 200 | C24: =SUM(C19) -> 250 | D24: =SUM(D19) -> 335 | E24: =SUM(E19) -> 785 | F24: =SUM(F19) -> 193 | G24: =SUM(G19) -> 205 | H24: =SUM(H19) -> 195 | I24: =SUM(I19) -> 593 | ... R24: =SUM(R19) -> 2278.5 | U24: pelle | V24: 0.2 | W24: 0 | X24: 0 | Y24: 0
A25: Slip on in pelle | B25: =SUM(B20) -> 32 | C25: =SUM(C20) -> 39 | D25: =SUM(D20) -> 53 | E25: =SUM(E20) -> 124 | F25: =SUM(F20) -> 12.4 | G25: =SUM(G20) -> 198 | H25: =SUM(H20) -> 186 | I25: =SUM(I20) -> 396.4 | ... R25: =SUM(R20) -> 1166.4 | U25: Scatola | Y25: 1
A26: Produzione | U26: filo | V26: 0 | W26: 6 | X26: 0 | Y26: 0
A27: Mocassino | B27: =B12+B17-B7 -> 10749 | C27: =C12+C17-C7 -> 9590 | D27: =D12+D17-D7 -> 10435 | E27: =E12+E17-E7 -> 30774 | F27: =F12+F17-F7 -> 10845 | G27: =G12+G17-G7 -> 12394.5 | H27: =H12+H17-H7 -> 12464.5 | I27: =I12+I17-I7 -> 35704 | J27: 12580.5 | K27: 12053.5 | L27: 11503 | M27: 36137 | N27: 10673.5 | O27: 9156.5 | P27: 8954 | Q27: =SUM(N27:P27) -> 28784 | R27: =Q27+M27+I27+E27 -> 131399 | U27: suole | V27: 0 | W27: 0 | X27: 1 | Y27: 0
A28: Decollete' | B28: =B13+B18-B8 -> 7644 | C28: =C13+C18-C8 -> 6945 | D28: =D13+D18-D8 -> 8187 | E28: =E13+E18-E8 -> 22776 | F28: =F13+F18-F8 -> 8683 | G28: =G13+G18-G8 -> 8618 | H28: =H13+H18-H8 -> 9322 | I28: =I13+I18-I8 -> 26623 | J28: 3830 | K28: 8140 | L28: 8561 | M28: 20531 | N28: 7771 | O28: 7605 | P28: 6958 | Q28: =SUM(N28:P28) -> 22334 | R28: =Q28+M28+I28+E28 -> 92264
A29: All Star | B29: =B14+B19-B9 -> 2199 | C29: =C14+C19-C9 -> 2050 | D29: =D14+D19-D9 -> 2585 | E29: =E14+E19-E9 -> 6834 | F29: =F14+F19-F9 -> 3208 | G29: =G14+G19-G9 -> 3872 | H29: =H14+H19-H9 -> 4090 | I29: =I14+I19-I9 -> 11170 | J29: 3907.5 | K29: 4037.5 | L29: 3925 | M29: 11870 | N29: 3124 | O29: 2813 | P29: 2008 | Q29: =SUM(N29:P29) -> 7945 | R29: =Q29+M29+I29+E29 -> 37819
A30: Slip on in pelle | B30: =B15+B20-B10 -> 672 | C30: =C15+C20-C10 -> 647 | D30: =D15+D20-D10 -> 794 | E30: =E15+E20-E10 -> 2113 | F30: =F15+F20-F10 -> 1019.4 | G30: =G15+G20-G10 -> 1425.6 | H30: =H15+H20-H10 -> 1308 | I30: =I15+I20-I10 -> 3753 | J30: 623 | K30: 634 | L30: 560 | M30: =SUM(J30:L30) -> 1817 | N30: 496 | O30: 439 | P30: 491 | Q30: =SUM(N30:P30) -> 1426 | R30: =Q30+M30+I30+E30 -> 9109 | T30: Linea classica Slip on in pelle | U30: Tempo Uomo | V30: 0.08 | W30: 0.42 | X30: 0.08 | Y30: 0.12
U31: Tempo Macchina | V31: 0.08 | W31: 0.42 | X31: 0.01 | Y31: 0.08
U32: Scarto | V32: 0.02 | W32: 0 | X32: 0 | Y32: 0
U33: Pelle | V33: 0.25 | W33: 0 | X33: 0 | Y33: 0
U34: Filo | V34: 0 | W34: 7 | X34: 1 | Y34: 0
A35: Piano dei consumi di materie prime | U35: Suole | V35: 0 | W35: 0 | X35: 1 | Y35: 0
U36: Scatola(opzionale) | V36: 0 | W36: 0 | X36: 0 | Y36: 1
A37: LUREX | B37: GEN. | C37: FEB. | D37: MAR. | E37: I TRIM | F37: APR. | G37: MAG. | H37: GIU. | I37: II TRIM | J37: LUG. | K37: AGO. | L37: SET. | M37: III TRIM | N37: OTT. | O37: NOV. | P37: DIC. | Q37: IV TRIM | R37: Totale
A38: Scatola
A39: linea sportiva All Star | B39: =B29*$Y25 -> 2199 | C39: =C29*$Y25 -> 2050 | D39: =D29*$Y25 -> 2585 | E39: =SUM(B39:D39) -> 6834 | F39: =F29*$Y25 -> 3208 | G39: =G29*$Y25 -> 3872 | H39: =H29*$Y25 -> 4090 | I39: =H39+G39+F39 -> 11170 | J39: =J29*$Y25 -> 3907.5 | K39: =K29*$Y25 -> 4037.5 | L39: =L29*$Y25 -> 3925 | M39: =SUM(L39+K39+J39) -> 11870 | N39: =N29*$Y25 -> 3124 | O39: =O29*$Y25 -> 2813 | P39: =P29*$Y25 -> 2008 | Q39: =SUM(N39:P39) -> 7945 | R39: =Q39+M39+I39+E39 -> 37819
A40: linea classica slip on in pelle | B40: =B30*$Y36 -> 672 | C40: =C30*$Y36 -> 647 | D40: =D30*$Y36 -> 794 | E40: =SUM(B40:D40) -> 2113 | F40: =F30*$Y36 -> 1019.4 | G40: =G30*$Y36 -> 1425.6 | H40: =H30*$Y36 -> 1308 | I40: =SUM(F40:H40) -> 3753 | J40: =J30*$Y36 -> 623 | K40: =K30*$Y36 -> 634 | L40: =L30*$Y36 -> 560 | M40: =SUM(J40:L40) -> 1817 | N40: =N30*$Y36 -> 496 | O40: =O30*$Y36 -> 439 | P40: =P30*$Y36 -> 491 | Q40: =SUM(N40:P40) -> 1426 | R40: 6176
A41: Totale | B41: =SUM(B39:B40) -> 2871 | C41: =SUM(C39:C40) -> 2697 | D41: =SUM(D39:D40) -> 3379 | E41: =SUM(B41:D41) -> 8947 | F41: =SUM(F39:F40) -> 4227.4 | G41: =SUM(G39:G40) -> 5297.6 | H41: =SUM(H39:H40) -> 5398 | I41: =SUM(F41:H41) -> 14923 | J41: =SUM(J39:J40) -> 4530.5 | K41: =SUM(K39:K40) -> 4671.5 | L41: =SUM(L39:L40) -> 4485 | M41: =SUM(J41:L41) -> 13687 | N41: =SUM(N39:N40) -> 3620 | O41: =SUM(O39:O40) -> 3252 | P41: =SUM(P39:P40) -> 2499 | Q41: =Q39+Q40 -> 9371 | R41: =Q41+M41+I41+E41 -> 46928 | U41: Prezzo standard medio annuo
A42: Pelle
A43: linea classica mocassino | B43: =B27*$V8 -> 3224.7 | C43: =C27*$V8 -> 2877 | D43: =D27*$V8 -> 3130.5 | E43: =SUM(B43:D43) -> 9232.2 | F43: =F27*$V8 -> 3253.5 | G43: =G27*$V8 -> 3718.35 | H43: =H27*$V8 -> 3739.35 | I43: =SUM(F43:H43) -> 10711.2 | J43: =J27*$V8 -> 3774.15 | K43: =K27*$V8 -> 3616.05 | L43: =L27*$V8 -> 3450.9 | M43: =SUM(J43:L43) -> 10841.1 | N43: =N27*$V8 -> 3202.05 | O43: =O27*$V8 -> 2746.95 | P43: =P27*$V8 -> 2686.2 | Q43: =SUM(N43:P43) -> 8635.2 | R43: =SUM(Q43+M43+I43+E43) -> 39419.7 | V43: Media | W43: Media
A44: linea classica decollette' | B44: =B28*$V16 -> 1911 | C44: =C28*$V16 -> 1736.25 | D44: =D28*$V16 -> 2046.75 | E44: =SUM(B44:D44) -> 5694 | F44: =F28*$V16 -> 2170.75 | G44: =G28*$V16 -> 2154.5 | H44: =H28*$V16 -> 2330.5 | I44: =SUM(F44:H44) -> 6655.75 | J44: =J28*$V16 -> 957.5 | K44: =K28*$V16 -> 2035 | L44: =L28*$V16 -> 2140.25 | M44: =SUM(J44:L44) -> 5132.75 | N44: =N28*$V16 -> 1942.75 | O44: =O28*$V16 -> 1901.25 | P44: =P28*$V16 -> 1739.5 | Q44: =SUM(N44:P44) -> 5583.5 | R44: =SUM(Q44+M44+I44+E44) -> 23066 | V44: 1 semestre | W44: 2 semestre
A45: linea sportiva All Star | B45: =B29*$V24 -> 439.8 | C45: =C29*$V24 -> 410 | D45: =D29*$V24 -> 517 | E45: =SUM(B45:D45) -> 1366.8 | F45: =F29*$V24 -> 641.6 | G45: =G29*$V24 -> 774.4 | H45: =H29*$V24 -> 818 | I45: =F45+G45+H45 -> 2234 | J45: =J29*$V24 -> 781.5 | K45: =K29*$V24 -> 807.5 | L45: =L29*$V24 -> 785 | M45: =J45+K45+L45 -> 2374 | N45: =N29*$V24 -> 624.8 | O45: =O29*$V24 -> 562.6 | P45: =P29*$V24 -> 401.6 | Q45: =N45+O45+P45 -> 1589 | R45: =Q45+M45+I45+E45 -> 7563.8 | U45: Scatola | V45: 5 | W45: 5
A46: linea classica slip on in pelle | B46: =B30*$V33 -> 168 | C46: =C30*$V33 -> 161.75 | D46: =D30*$V33 -> 198.5 | E46: =D46+C46+B46 -> 528.25 | F46: =F30*$V33 -> 254.85 | G46: =G30*$V33 -> 356.4 | H46: =H30*$V33 -> 327 | I46: =H46+G46+F46 -> 938.25 | J46: =J30*$V33 -> 155.75 | K46: =K30*$V33 -> 158.5 | L46: =L30*$V33 -> 140 | M46: =L46+K46+J46 -> 454.25 | N46: =N30*$V33 -> 124 | O46: =O30*$V33 -> 109.75 | P46: =P30*$V33 -> 122.75 | Q46: =P46+O46+N46 -> 356.5 | R46: =Q46+M46+I46+E46 -> 2277.25 | U46: Pelle | V46: 36.78 | W46: 36.67
A47: Totale | B47: =SUM(B43:B46) -> 5743.5 | C47: =SUM(C43:C46) -> 5185 | D47: =SUM(D43:D46) -> 5892.75 | E47: =SUM(B47:D47) -> 16821.25 | F47: =SUM(F43:F46) -> 6320.7 | G47: =SUM(G43:G46) -> 7003.65 | H47: =SUM(H43:H46) -> 7214.85 | I47: =SUM(F47:H47) -> 20539.2 | J47: =SUM(J43:J46) -> 5668.9 | K47: =SUM(K43:K46) -> 6617.05 | L47: =SUM(L43:L46) -> 6516.15 | M47: =SUM(J47:L47) -> 18802.1 | N47: =SUM(N43:N46) -> 5893.6 | O47: =SUM(O43:O46) -> 5320.55 | P47: =SUM(P43:P46) -> 4950.05 | Q47: =SUM(Q43:Q46) -> 16164.2 | R47: =SUM(R43:R46) -> 72326.75 | U47: Filo | V47: 0.0031 | W47: 0.003
A48: Filo | U48: Suole | V48: 5 | W48: 5
A49: linea classica mocassino | B49: =B27*$W9 -> 85992 | C49: =C27*$W9 -> 76720 | D49: =D27*$W9 -> 83480 | E49: =SUM(B49:D49) -> 246192 | F49: =F27*$W9 -> 86760 | G49: =G27*$W9 -> 99156 | H49: =H27*$W9 -> 99716 | I49: =SUM(F49:H49) -> 285632 | J49: =J27*$W9 -> 100644 | K49: =K27*$W9 -> 96428 | L49: =L27*$W9 -> 92024 | M49: =SUM(J49:L49) -> 289096 | N49: =N27*$W9 -> 85388 | O49: =O27*$W9 -> 73252 | P49: =P27*$W9 -> 71632 | Q49: =SUM(N49:P49) -> 230272 | R49: =SUM(Q49+M49+I49+E49) -> 1051192
A50: linea classica decollette' | B50: =B28*$W17 -> 53508 | C50: =C28*$W17 -> 48615 | D50: =D28*$W17 -> 57309 | E50: =SUM(B50:D50) -> 159432 | F50: =F28*$W17 -> 60781 | G50: =G28*$W17 -> 60326 | H50: =H28*$W17 -> 65254 | I50: =SUM(F50:H50) -> 186361 | J50: =J28*$W17 -> 26810 | K50: =K28*$W17 -> 56980 | L50: =L28*$W17 -> 59927 | M50: =SUM(J50:L50) -> 143717 | N50: =N28*$W17 -> 54397 | O50: =O28*$W17 -> 53235 | P50: =P28*$W17 -> 48706 | Q50: =SUM(N50:P50) -> 156338 | R50: =Q50+M50+I50+E50 -> 645848
A51: linea sportiva All Star | B51: =B29*$W26 -> 13194 | C51: =C29*$W26 -> 12300 | D51: =D29*$W26 -> 15510 | E51: =SUM(B51:D51) -> 41004 | F51: =F29*$W26 -> 19248 | G51: =G29*$W26 -> 23232 | H51: =H29*$W26 -> 24540 | I51: =SUM(F51:H51) -> 67020 | J51: =J29*$W26 -> 23445 | K51: =K29*$W26 -> 24225 | L51: =L29*$W26 -> 23550 | M51: =SUM(J51:L51) -> 71220 | N51: =N29*$W26 -> 18744 | O51: =O29*$W26 -> 16878 | P51: =P29*$W26 -> 12048 | Q51: =SUM(N51:P51) -> 47670 | R51: =Q51+M51+I51+E51 -> 226914
A52: linea classica slip on in pelle | B52: =B30*($W34+$X34) -> 5376 | C52: =C30*($W34+$X34) -> 5176 | D52: =D30*($W34+$X34) -> 6352 | E52: =D52+C52+B52 -> 16904 | F52: =F30*($W34+$X34) -> 8155.2 | G52: =G30*($W34+$X34) -> 11404.8 | H52: =H30*($W34+$X34) -> 10464 | I52: =H52+G52+F52 -> 30024 | J52: =J30*($W34+$X34) -> 4984 | K52: =K30*($W34+$X34) -> 5072 | L52: =L30*($W34+$X34) -> 4480 | M52: =L52+K52+J52 -> 14536 | N52: =N30*($W34+$X34) -> 3968 | O52: =O30*($W34+$X34) -> 3512 | P52: =P30*($W34+$X34) -> 3928 | Q52: =P52+O52+N52 -> 11408 | R52: =Q52+M52+I52+E52 -> 72872
A53: Totale | B53: =SUM(B49:B52) -> 158070 | C53: =SUM(C49:C52) -> 142811 | D53: =SUM(D49:D52) -> 162651 | E53: =B53+C53+D53 -> 463532 | F53: =SUM(F49:F52) -> 174944.2 | G53: =SUM(G49:G52) -> 194118.8 | H53: =SUM(H49:H52) -> 199974 | I53: =F53+G53+H53 -> 569037 | J53: =SUM(J49:J52) -> 155883 | K53: =SUM(K49:K52) -> 182705 | L53: =SUM(L49:L52) -> 179981 | M53: =J53+K53+L53 -> 518569 | N53: =SUM(N49:N52) -> 162497 | O53: =SUM(O49:O52) -> 146877 | P53: =SUM(P49:P52) -> 136314 | Q53: =P53+O53+N53 -> 445688 | R53: =SUM(R49:R52) -> 1996826
A54: Suole
A55: linea classica mocassino | B55: =B27*$X10 -> 10749 | C55: =C27*$X10 -> 9590 | D55: =D27*$X10 -> 10435 | E55: =SUM(B55:D55) -> 30774 | F55: =F27*$X10 -> 10845 | G55: =G27*$X10 -> 12394.5 | H55: =H27*$X10 -> 12464.5 | I55: =SUM(F55:H55) -> 35704 | J55: =J27*$X10 -> 12580.5 | K55: =K27*$X10 -> 12053.5 | L55: =L27*$X10 -> 11503 | M55: =SUM(J55:L55) -> 36137 | N55: =N27*$X10 -> 10673.5 | O55: =O27*$X10 -> 9156.5 | P55: =P27*$X10 -> 8954 | Q55: =SUM(N55:P55) -> 28784 | R55: =SUM(Q55+M55+I55+E55) -> 131399
A56: linea classica decollette' | B56: =B28*$X18 -> 7644 | C56: =C28*$X18 -> 6945 | D56: =D28*$X18 -> 8187 | E56: =SUM(B56:D56) -> 22776 | F56: =F28*$X18 -> 8683 | G56: =G28*$X18 -> 8618 | H56: =H28*$X18 -> 9322 | I56: =SUM(F56:H56) -> 26623 | J56: =J28*$X18 -> 3830 | K56: =K28*$X18 -> 8140 | L56: =L28*$X18 -> 8561 | M56: =SUM(J56:L56) -> 20531 | N56: =N28*$X18 -> 7771 | O56: =O28*$X18 -> 7605 | P56: =P28*$X18 -> 6958 | Q56: =SUM(N56:P56) -> 22334 | R56: =Q56+M56+I56+E56 -> 92264
A57: linea sportiva All Star | B57: =B29*$X27 -> 2199 | C57: =C29*$X27 -> 2050 | D57: =D29*$X27 -> 2585 | E57: =SUM(B57:D57) -> 6834 | F57: =F29*$X27 -> 3208 | G57: =G29*$X27 -> 3872 | H57: =H29*$X27 -> 4090 | I57: =SUM(F57:H57) -> 11170 | J57: =J29*$X27 -> 3907.5 | K57: =K29*$X27 -> 4037.5 | L57: =L29*$X27 -> 3925 | M57: =SUM(J57:L57) -> 11870 | N57: =N29*$X27 -> 3124 | O57: =O29*$X27 -> 2813 | P57: =P29*$X27 -> 2008 | Q57: =P57+N57+O57 -> 7945 | R57: =SUM(Q57+M57+I57+E57) -> 37819
A58: linea classica slip on in pelle | B58: =B30*$X35 -> 672 | C58: =C30*$X35 -> 647 | D58: =D30*$X35 -> 794 | E58: =D58+C58+B58 -> 2113 | F58: =F30*$X35 -> 1019.4 | G58: =G30*$X35 -> 1425.6 | H58: =H30*$X35 -> 1308 | I58: =H58+G58+F58 -> 3753 | J58: =J30*$X35 -> 623 | K58: =K30*$X35 -> 634 | L58: =L30*$X35 -> 560 | M58: =L58+K58+J58 -> 1817 | N58: =N30*$X35 -> 496 | O58: =O30*$X35 -> 439 | P58: =P30*$X35 -> 491 | Q58: =P58+O58+N58 -> 1426 | R58: =Q58+M58+I58+E58 -> 9109
A59: Totale | B59: =SUM(B55:B58) -> 21264 | C59: =SUM(C55:C58) -> 19232 | D59: =SUM(D55:D58) -> 22001 | E59: =D59+C59+B59 -> 62497 | F59: =SUM(F55:F58) -> 23755.4 | G59: =SUM(G55:G58) -> 26310.1 | H59: =SUM(H55:H58) -> 27184.5 | I59: =G59+F59 -> 50065.5 | J59: =SUM(J55:J58) -> 20941 | K59: =SUM(K55:K58) -> 24865 | L59: =SUM(L55:L58) -> 24549 | M59: =L59+K59+J59 -> 70355 | N59: =SUM(N55:N58) -> 22064.5 | O59: =SUM(O55:O58) -> 20013.5 | P59: =SUM(P55:P58) -> 18411 | Q59: =P59+O59+N59 -> 60489 | R59: =SUM(R55:R58) -> 270591
A63: Budget dei costi di consumo di materie prime
A64: LUREX 1 | B64: GEN. | C64: FEB. | D64: MAR. | E64: I TRIM | F64: APR. | G64: MAG. | H64: GIU. | I64: II TRIM | J64: LUG. | K64: AGO. | L64: SET. | M64: III TRIM | N64: OTT. | O64: NOV. | P64: DIC. | Q64: IV TRIM | R64: Totale
A65: Scatola
A66: All Star | B66: =B39*$V$45 -> 10995 | C66: =C39*$V$45 -> 10250 | D66: =D39*$V$45 -> 12925 | E66: =SUM(B66:D66) -> 34170 | F66: =F39*$V$45 -> 16040 | G66: =G39*$V$45 -> 19360 | H66: =H39*$V$45 -> 20450 | I66: =F66+G66+H66 -> 55850 | J66: =J39*$W$45 -> 19537.5 | K66: =K39*$W$45 -> 20187.5 | L66: =L39*$W$45 -> 19625 | M66: =J66+K66+L66 -> 59350 | N66: =N39*$W$45 -> 15620 | O66: =O39*$W$45 -> 14065 | P66: =P39*$W$45 -> 10040 | Q66: =N66+O66+P66 -> 39725 | R66: =E66+I66+M66+Q66 -> 189095
A67: Slip on in pelle | B67: =B40*$V$45 -> 3360 | C67: =C40*$V$45 -> 3235 | D67: =D40*$V$45 -> 3970 | E67: =SUM(B67:D67) -> 10565 | F67: =F40*$V$45 -> 5097 | G67: =G40*$V$45 -> 7128 | H67: =H40*$V$45 -> 6540 | I67: =F67+G67+H67 -> 18765 | J67: =J40*$W$45 -> 3115 | K67: =K40*$W$45 -> 3170 | L67: =L40*$W$45 -> 2800 | M67: =J67+K67+L67 -> 9085 | N67: =N40*$W$45 -> 2480 | O67: =O40*$W$45 -> 2195 | P67: =P40*$W$45 -> 2455 | Q67: =N67+O67+P67 -> 7130 | R67: =E67+I67+M67+Q67 -> 45545
A68: Totale | B68: =SUM(B66:B67) -> 14355 | C68: =SUM(C66:C67) -> 13485 | D68: =SUM(D66:D67) -> 16895 | E68: =SUM(E66:E67) -> 44735 | F68: =F66+F67 -> 21137 | G68: =G66+G67 -> 26488 | H68: =H66+H67 -> 26990 | I68: =E68+F68+G68+H68 -> 119350 | J68: =J66+J67 -> 22652.5 | K68: =K66+K67 -> 23357.5 | L68: =L66+L67 -> 22425 | M68: =J68+K68+L68 -> 68435 | N68: =N66+N67 -> 18100 | O68: =O66+O67 -> 16260 | P68: =P66+P67 -> 12495 | Q68: =N68+O68+P68 -> 46855 | R68: =E68+I68+M68+Q68 -> 279375
A69: Pelle
A70: Mocassino | B70: =B43*$V$46 -> 118604.47 | C70: =C43*$V$46 -> 105816.06 | D70: =D43*$V$46 -> 115139.79 | E70: =SUM(B70:D70) -> 339560.32 | F70: =F43*$V$46 -> 119663.73 | G70: =G43*$V$46 -> 136760.91 | H70: =H43*$V$46 -> 137533.29 | I70: =F70+G70+H70 -> 393957.94 | J70: =J43*$W$46 -> 138398.08 | K70: =K43*$W$46 -> 132600.55 | L70: =L43*$W$46 -> 126544.5 | M70: =J70+K70+L70 -> 397543.14 | N70: =N43*$W$46 -> 117419.17 | O70: =O43*$W$46 -> 100730.66 | P70: =P43*$W$46 -> 98502.954 | Q70: =N70+O70+P70 -> 316652.78 | R70: =E70+I70+M70+Q70 -> 1447714.2
A71: Decollete' | B71: =B44*$V$46 -> 70286.58 | C71: =C44*$V$46 -> 63859.275 | D71: =D44*$V$46 -> 75279.465 | E71: =SUM(B71:D71) -> 209425.32 | F71: =F44*$V$46 -> 79840.185 | G71: =G44*$V$46 -> 79242.51 | H71: =H44*$V$46 -> 85715.79 | I71: =F71+G71+H71 -> 244798.49 | J71: =J44*$W$46 -> 35111.525 | K71: =K44*$W$46 -> 74623.45 | L71: =L44*$W$46 -> 78482.967 | M71: =J71+K71+L71 -> 188217.94 | N71: =N44*$W$46 -> 71240.643 | O71: =O44*$W$46 -> 69718.838 | P71: =P44*$W$46 -> 63787.465 | Q71: =N71+O71+P71 -> 204746.95 | R71: =E71+I71+M71+Q71 -> 847188.69
A72: All Star | B72: =B45*$V$46 -> 16175.844 | C72: =C45*$V$46 -> 15079.8 | D72: =D45*$V$46 -> 19015.26 | E72: =SUM(B72:D72) -> 50270.904 | F72: =45*$V$46 -> 1655.1 | G72: =G45*$V$46 -> 28482.432 | H72: =H45*$V$46 -> 30086.04 | I72: =F72+G72+H72 -> 60223.572 | J72: =J45*$W$46 -> 28657.605 | K72: =K45*$W$46 -> 29611.025 | L72: =L45*$W$46 -> 28785.95 | M72: =J72+K72+L72 -> 87054.58 | N72: =N45*$W$46 -> 22911.416 | O72: =O45*$W$46 -> 20630.542 | P72: =P45*$W$46 -> 14726.672 | Q72: =N72+O72+P72 -> 58268.63 | R72: =E72+I72+M72+Q72 -> 255817.69
A73: Slip on in pelle | B73: =B46*$V$46 -> 6179.04 | C73: =C46*$V$46 -> 5949.165 | D73: =D46*$V$46 -> 7300.83 | E73: =SUM(B73:D73) -> 19429.035 | F73: =F46*$V$46 -> 9373.383 | G73: =G46*$V$46 -> 13108.392 | H73: =H46*$V$46 -> 12027.06 | I73: =F73+G73+H73 -> 34508.835 | J73: =J46*$W$46 -> 5711.3525 | K73: =K46*$W$46 -> 5812.195 | L73: =L46*$W$46 -> 5133.8 | M73: =J73+K73+L73 -> 16657.347 | N73: =N46*$W$46 -> 4547.08 | O73: =P46*$W$46 -> 4501.2425 | P73: =P46*$W$46 -> 4501.2425 | Q73: =N73+O73+P73 -> 13549.565 | R73: =E73+I73+M73+Q73 -> 84144.783
A74: Totale | B74: =SUM(B70:B73) -> 211245.93 | C74: =SUM(C70:C73) -> 190704.3 | D74: =SUM(D70:D73) -> 216735.35 | E74: =SUM(B74:D74) -> 618685.57 | F74: =F70+F71+F72+F73 -> 210532.4 | G74: =G70+G71+G72+G73 -> 257594.25 | H74: =H70+H71+H72 -> 253335.12 | I74: =F74+G74+H74 -> 721461.77 | J74: =J70+J71+J72+J73 -> 207878.56 | K74: =K70+K71+K72+K73 -> 242647.22 | L74: =L70+L71+L72+L73 -> 238947.22 | M74: =J74+K74+L74 -> 689473.01 | N74: =N70+N71+N72+N73 -> 216118.31 | O74: =O70+O71+O72+O73 -> 195581.28 | P74: =P70++P72+P73 -> 117730.87 | Q74: =N74+O74+P74 -> 529430.46 | R74: =E74+M74+I74+Q74 -> 2559050.8
A75: Filo
A76: Mocassino | B76: =B49*$V$47 -> 266.5752 | C76: =C49*$V$47 -> 237.832 | D76: =D49*$V$47 -> 258.788 | E76: =B76+C76+D76 -> 763.1952 | F76: =F49*$V$47 -> 268.956 | G76: =G49*$V$47 -> 307.3836 | H76: =H49*$V$47 -> 309.1196 | I76: =F76+G76+H76 -> 885.4592 | J76: =J49*$W$47 -> 301.932 | K76: =K49*$W$47 -> 289.284 | L76: =L49*$W$47 -> 276.072 | M76: =J76+K76+L76 -> 867.288 | N76: =N49*$W$47 -> 256.164 | O76: =O49*$W$47 -> 219.756 | P76: =P49*$W$47 -> 214.896 | Q76: =N76+O76+P76 -> 690.816 | R76: =E76+I76+M76+Q76 -> 3206.7584
A77: Decollete' | B77: =B50*$V$47 -> 165.8748 | C77: =C50*$V$47 -> 150.7065 | D77: =D50*$V$47 -> 177.6579 | E77: =B77+C77+D77 -> 494.2392 | F77: =F50*$V$47 -> 188.4211 | G77: =G50*$V$47 -> 187.0106 | H77: =H50*$V$47 -> 202.2874 | I77: =F77+G77+H77 -> 577.7191 | J77: =J50*$W$47 -> 80.43 | K77: =K50*$W$47 -> 170.94 | L77: =L50*$W$47 -> 179.781 | M77: =J77+K77+L77 -> 431.151 | N77: =N50*$W$47 -> 163.191 | O77: =O50*$W$47 -> 159.705 | P77: =P50*$W$47 -> 146.118 | Q77: =N77+O77+P77 -> 469.014 | R77: =E77+I77+M77+Q77 -> 1972.1233
A78: All Star | B78: =B51*$V$47 -> 40.9014 | C78: =C51*$V$47 -> 38.13 | D78: =D51*$V$47 -> 48.081 | E78: =B78+C78+D78 -> 127.1124 | F78: =F51*$V$47 -> 59.6688 | G78: =G51*$V$47 -> 72.0192 | H78: =H51*$V$47 -> 76.074 | I78: =F78+G78+H78 -> 207.762 | J78: =J51*$W$47 -> 70.335 | K78: =K51*$W$47 -> 72.675 | L78: =L51*$W$47 -> 70.65 | M78: =J78+K78+L78 -> 213.66 | N78: =N51*$W$47 -> 56.232 | O78: =O51*$W$47 -> 50.634 | P78: =P51*$W$47 -> 36.144 | Q78: =N78+O78+P78 -> 143.01 | R78: =E78+I78+M78+Q78 -> 691.5444
A79: Slip on in pelle | B79: =B52*$V$47 -> 16.6656 | C79: =C52*$V$47 -> 16.0456 | D79: =D52*$V$47 -> 19.6912 | E79: =B79+C79+D79 -> 52.4024 | F79: =F52*$V$47 -> 25.28112 | G79: =G52*$V$47 -> 35.35488 | H79: =H52*$V$47 -> 32.4384 | I79: =F79+G79+H79 -> 93.0744 | J79: =J52*$W$47 -> 14.952 | K79: =K52*$W$47 -> 15.216 | L79: =L52*$W$47 -> 13.44 | M79: =J79+K79+L79 -> 43.608 | N79: =N52*$W$47 -> 11.904 | O79: =O52*$W$47 -> 10.536 | P79: =P52*$W$47 -> 11.784 | Q79: =N79+O79+P79 -> 34.224 | R79: =E79+I79+M79+Q79 -> 223.3088
A80: Totale | B80: =SUM(B76:B79) -> 490.017 | C80: =C76+C77+C78+C79 -> 442.7141 | D80: =D76+D77+D78+D79 -> 504.2181 | E80: =B80+C80+D80 -> 1436.9492 | F80: =F76+F77+F78+F79 -> 542.32702 | G80: =G76+G77+G78+G79 -> 601.76828 | H80: =H76+H77+H78+H79 -> 619.9194 | I80: =F80+G80+H80 -> 1764.0147 | J80: =SUM(J76:J79) -> 467.649 | K80: =SUM(K76:K79) -> 548.115 | L80: =L76+L77+L78+L79 -> 539.943 | M80: =J80+K80+L80 -> 1555.707 | N80: =N76+N77+N78+N79 -> 487.491 | O80: =O76++O78+O79 -> 280.926 | P80: =P76+P77+P78+P79 -> 408.942 | Q80: =N80+O80+P80 -> 1177.359 | R80: =E80+I80+M80+Q80 -> 5934.0299
A81: Suole
A82: Mocassino | B82: =B55*$V$48 -> 53745 | C82: =C55*$V$48 -> 47950 | D82: =D55*$V$48 -> 52175 | E82: =B82+C82+D82 -> 153870 | F82: =F55*$V$48 -> 54225 | G82: =G55*$V$48 -> 61972.5 | H82: =H55*$V$48 -> 62322.5 | I82: =F82+G82+H82 -> 178520 | J82: =J55*$W$48 -> 62902.5 | K82: =K55*$W$48 -> 60267.5 | L82: =L55*$W$48 -> 57515 | M82: =J82+K82+L82 -> 180685 | N82: =N49*$W$48 -> 426940 | O82: =O49*$W$48 -> 366260 | P82: =P49*$W$48 -> 358160 | Q82: =N82+O82+P82 -> 1151360 | R82: =E82+I82+M82+Q82 -> 1664435
A83: Decollete' | B83: =B56*$V$48 -> 38220 | C83: =C56*$V$48 -> 34725 | D83: =D56*$V$48 -> 40935 | E83: =B83+C83+D83 -> 113880 | F83: =F56*$V$48 -> 43415 | G83: =G56*$V$48 -> 43090 | H83: =H56*$V$48 -> 46610 | I83: =F83+G83+H83 -> 133115 | J83: =J56*$W$48 -> 19150 | K83: =K56*$W$48 -> 40700 | L83: =L56*$W$48 -> 42805 | M83: =J83+K83+L83 -> 102655 | N83: =N50*$W$48 -> 271985 | O83: =O50*$W$48 -> 266175 | P83: =P50*$W$48 -> 243530 | Q83: =N83+O83+P83 -> 781690 | R83: =E83+I83+M83+Q83 -> 1131340
A84: All Star | B84: =B57*$V$48 -> 10995 | C84: =C57*$V$48 -> 10250 | D84: =D57*$V$48 -> 12925 | E84: =B84+C84+D84 -> 34170 | F84: =F57*$V$48 -> 16040 | G84: =G57*$V$48 -> 19360 | H84: =H57*$V$48 -> 20450 | I84: =F84+G84+H84 -> 55850 | J84: =J57*$W$48 -> 19537.5 | K84: =K57*$W$48 -> 20187.5 | L84: =L57*$W$48 -> 19625 | M84: =J84+K84+L84 -> 59350 | N84: =N51*$W$48 -> 93720 | O84: =O51*$W$48 -> 84390 | P84: =P51*$W$48 -> 60240 | Q84: =N84+O84+P84 -> 238350 | R84: =E84+I84+M84+Q84 -> 387720
A85: Slip on in pelle | B85: =B58*$V$48 -> 3360 | C85: =C58*$V$48 -> 3235 | D85: =D58*$V$48 -> 3970 | E85: =B85+C85+D85 -> 10565 | F85: =F58*$V$48 -> 5097 | G85: =G58*$V$48 -> 7128 | H85: =H58*$V$48 -> 6540 | I85: =F85+G85+H85 -> 18765 | J85: =J58*$W$48 -> 3115 | K85: =K58*$V$48 -> 3170 | L85: =L58*$W$48 -> 2800 | M85: =J85+K85+L85 -> 9085 | N85: =N52*$W$48 -> 19840 | O85: =O52*$W$48 -> 17560 | P85: =P52*$W$48 -> 19640 | Q85: =N85+O85+P85 -> 57040 | R85: =E85+I85+M85+Q85 -> 95455
A86: Totale | B86: =SUM(B82:B85) -> 106320 | C86: =C82+C83+C84+C85 -> 96160 | D86: =D82+D83+D84+D85 -> 110005 | E86: =B86+C86+D86 -> 312485 | F86: =F82+F83+F84 -> 113680 | G86: =G82+G83+G84+G85 -> 131550.5 | H86: =H82+H83+H84+H85 -> 135922.5 | I86: =F86+G86+H86 -> 381153 | J86: =J82+J83+J84+J85 -> 104705 | K86: =K82+K83+K84+K85 -> 124325 | L86: =L82+L83+L84+L85 -> 122745 | M86: =J86+K86+L86 -> 351775 | N86: =N82+N83+N84+N85 -> 812485 | O86: =O82+O83+O84+O85 -> 734385 | P86: =P82+P83+P84+P85 -> 681570 | Q86: =N86+O86+P86 -> 2228440 | R86: =E86+I86+M86+Q86 -> 3273853
A92: Piano dei volumi acquisti/scorte di materie prime
A94: LUREX 1 | B94: GEN. | C94: FEB. | D94: MAR. | E94: I TRIM | F94: APR. | G94: MAG. | H94: GIU. | I94: II TRIM | J94: LUG. | K94: AGO. | L94: SET. | M94: III TRIM | N94: OTT. | O94: NOV. | P94: DIC. | Q94: IV TRIM | R94: Totale
A95: Scatola
A96: Rimanenze iniziali | B96: =B41*0.1 -> 287.1 | C96: =B97 -> 269.7 | D96: =C97 -> 337.9 | E96: =SUM(B96:D96) -> 894.7 | F96: =D97 -> 634.11 | G96: =F97 -> 794.64 | H96: =G97 -> 809.7 | I96: =SUM(F96:H96) -> 2238.45 | J96: =$H$97 -> 906.1 | K96: =J97 -> 934.3 | L96: =K97 -> 897 | M96: =SUM(J96:L96) -> 2737.4 | N96: =$L$97 -> 2053.05 | O96: =N97 -> 487.8 | P96: =O97 -> 249.9 | Q96: =SUM(N96:P96) -> 2790.75 | R96: =Q96+M96+I96+E96 -> 8661.3
A97: Rimanenze finali programmate | B97: =C41*0.1 -> 269.7 | C97: =D41*0.1 -> 337.9 | D97: =F41*0.15 -> 634.11 | E97: =SUM(B97:D97) -> 1241.71 | F97: =G41*0.15 -> 794.64 | G97: =H41*0.15 -> 809.7 | H97: =J41*0.2 -> 906.1 | I97: =SUM(F97:H97) -> 2510.44 | J97: =K41*0.2 -> 934.3 | K97: =L41*0.2 -> 897 | L97: =M41*0.15 -> 2053.05 | M97: =SUM(J97:L97) -> 3884.35 | N97: =O41*0.15 -> 487.8 | O97: =P41*0.1 -> 249.9 | P97: =B41*0.1 -> 287.1 | Q97: =SUM(N97:P97) -> 1024.8 | R97: =SUM(Q97+M97+I97+E97) -> 8661.3
A98: Rimanenze fin. effettive | B98: =B97 -> 269.7 | C98: =C97 -> 337.9 | D98: =D97 -> 634.11 | E98: =SUM(B98:D98) -> 1241.71 | F98: =F97 -> 794.64 | G98: =G97 -> 809.7 | H98: =H97 -> 906.1 | I98: =I97 -> 2510.44 | J98: =J97 -> 934.3 | K98: =K97 -> 897 | L98: =L97 -> 2053.05 | M98: =M97 -> 3884.35 | ... R98: =R97 -> 8661.3
A99: Totale Acquisti | B99: =SUM(B41+B97-B96) -> 2853.6 | C99: =SUM(C41+C97-C96) -> 2765.2 | D99: =SUM(D41+D97-D96) -> 3675.21 | E99: =SUM(B99:D99) -> 9294.01 | F99: =F41+F97-F96 -> 4387.93 | G99: =G41+G97-G96 -> 5312.66 | H99: =H41+H97-H96 -> 5494.4 | I99: =SUM(F99:H99) -> 15194.99 | J99: =J41+J97-J96 -> 4558.7 | K99: =K41+K97-K96 -> 4634.2 | L99: =L41+L97-L96 -> 5641.05 | M99: =SUM(J99:L99) -> 14833.95 | N99: =N41+N97-N96 -> 2054.75 | O99: =O41+O97-O96 -> 3014.1 | P99: =P41+P97-P96 -> 2536.2 | Q99: =SUM(N99:P99) -> 7605.05 | R99: =Q99+M99+I99+E99 -> 46928
A100: Pelle
A101: Rimanenze iniziali | B101: =B47*0.05 -> 287.175 | C101: =B102 -> 518.5 | D101: =C102 -> 589.275 | E101: =SUM(B101:D101) -> 1394.95 | F101: =D102 -> 948.105 | G101: =F102 -> 1750.9125 | H101: =G102 -> 1803.7125 | I101: =H101+G101+F101 -> 4502.73 | J101: =$H$102 -> 5134.8 | K101: =J102 -> 1654.2625 | L101: =K102 -> 1303.23 | M101: =L101+K101+J101 -> 8092.2925 | N101: =$L$102 -> 884.04 | O101: =N102 -> 798.0825 | P101: =O102 -> 495.005 | Q101: =P101+O101+N101 -> 2177.1275 | R101: =Q101+M101+I101+E101 -> 16167.1
A102: Rimanenze finali programmate | B102: =C47*0.1 -> 518.5 | C102: =D47*0.1 -> 589.275 | D102: =F47*0.15 -> 948.105 | E102: =SUM(B102:D102) -> 2055.88 | F102: =G47*0.25 -> 1750.9125 | G102: =H47*0.25 -> 1803.7125 | H102: =I47*0.25 -> 5134.8 | I102: =H102+G102+F102 -> 8689.425 | J102: =K47*0.25 -> 1654.2625 | K102: =L47*0.2 -> 1303.23 | L102: =N47*0.15 -> 884.04 | M102: =L102+K102+J102 -> 3841.5325 | N102: =O47*0.15 -> 798.0825 | O102: =P47*0.1 -> 495.005 | P102: =B47*0.1 -> 574.35 | Q102: =P102+O102+N102 -> 1867.4375 | R102: =Q102+M102+I102+E102 -> 16454.275
A103: Rimanenze fin. effettive | B103: =B102 -> 518.5 | C103: =C102 -> 589.275 | D103: =D102 -> 948.105 | E103: =SUM(B103:D103) -> 2055.88 | F103: =F102 -> 1750.9125 | G103: =G102 -> 1803.7125 | H103: =H102 -> 5134.8 | I103: =I102 -> 8689.425 | J103: =J102 -> 1654.2625 | K103: =K102 -> 1303.23 | L103: =L102 -> 884.04 | M103: =M102 -> 3841.5325 | ... R103: =R102 -> 16454.275
A104: Totale Acquisti | B104: =SUM(B47+B102-B101) -> 5974.825 | C104: =SUM(C47+C102-C101) -> 5255.775 | D104: =SUM(D47+D102-D101) -> 6251.58 | E104: =SUM(B104:D104) -> 17482.18 | F104: =F47+F102-F101 -> 7123.5075 | G104: =G47+G102-G101 -> 7056.45 | H104: =H47+H102-H101 -> 10545.938 | I104: =H104+G104+F104 -> 24725.895 | J104: =J47+J102-J101 -> 2188.3625 | K104: =K47+K102-K101 -> 6266.0175 | L104: =L47+L102-L101 -> 6096.96 | M104: =L104+K104+J104 -> 14551.34 | N104: =N47+N102-N101 -> 5807.6425 | O104: =O47+O102-O101 -> 5017.4725 | P104: =P47+P102-P101 -> 5029.395 | Q104: =P104+O104+N104 -> 15854.51 | R104: =R101+R102+R103 -> 49075.65
A105: Filo
A106: Rimanenze iniziali | B106: =B53*0.1 -> 15807 | C106: =B107 -> 14281.1 | D106: =C107 -> 16265.1 | E106: =SUM(B106:D106) -> 46353.2 | F106: =D107 -> 26241.63 | G106: =F107 -> 38823.76 | H106: =G107 -> 39994.8 | I106: =F106+G106+H106 -> 105060.19 | J106: =H107 -> 31176.6 | K106: =J107 -> 36541 | L106: =K107 -> 35996.2 | M106: =J106+K106+L106 -> 103713.8 | N106: =L107 -> 24374.55 | O106: =N107 -> 22031.55 | P106: =O107 -> 13631.4 | Q106: =N106+O106+P106 -> 60037.5 | R106: =Q106+M106+I106+E106 -> 315164.69
A107: Rimanenze finali programmate | B107: =C53*0.1 -> 14281.1 | C107: =D53*0.1 -> 16265.1 | D107: =F53*0.15 -> 26241.63 | E107: =SUM(B107:D107) -> 56787.83 | F107: =G53*0.2 -> 38823.76 | G107: =H53*0.2 -> 39994.8 | H107: =J53*0.2 -> 31176.6 | I107: =F107+G107+H107 -> 109995.16 | J107: =K53*0.2 -> 36541 | K107: =L53*0.2 -> 35996.2 | L107: =N53*0.15 -> 24374.55 | M107: =J107+K107+L107 -> 96911.75 | N107: =O53*0.15 -> 22031.55 | O107: =P53*0.1 -> 13631.4 | P107: =B53*0.1 -> 15807 | Q107: =N107+O107+P107 -> 51469.95 | R107: =Q107+M107+I107+E107 -> 315164.69
A108: Rimanenze fin. effettive | B108: =B107 -> 14281.1 | C108: =C107 -> 16265.1 | D108: =D107 -> 26241.63 | E108: =SUM(B108:D108) -> 56787.83 | F108: =F107 -> 38823.76 | G108: =G107 -> 39994.8 | H108: =H107 -> 31176.6 | I108: =F108+G108+H108 -> 109995.16 | J108: =J107 -> 36541 | K108: =K107 -> 35996.2 | L108: =L107 -> 24374.55 | M108: =J108+K108+L108 -> 96911.75 | N108: =N107 -> 22031.55 | O108: =O107 -> 13631.4 | P108: =P107 -> 15807 | Q108: =N108+O108+P108 -> 51469.95 | R108: =Q108+M108+I108+E108 -> 315164.69
A109: Totale Acquisti | B109: =SUM(B53+B107-B106) -> 156544.1 | C109: =SUM(C53+C107-C106) -> 144795 | D109: =SUM(D53+D107-D106) -> 172627.53 | E109: =SUM(B109:D109) -> 473966.63 | F109: =F53+F107-F106 -> 187526.33 | G109: =H53+G107-G106 -> 201145.04 | H109: =H53+H107-H106 -> 191155.8 | I109: =F109+G109+H109 -> 579827.17 | J109: =J53+J107-J106 -> 161247.4 | K109: =K53+K107-K106 -> 182160.2 | L109: =L53+L107-L106 -> 168359.35 | M109: =J109+K109+L110 -> 343407.6 | N109: =N53+N107-N106 -> 160154 | O109: =O53+O107-O106 -> 138476.85 | P109: =P59+P107-P106 -> 20586.6 | Q109: =N109+O109+P109 -> 319217.45 | R109: =R106+R107+R108 -> 945494.07
A110: Suole
...

Sheet Foglio1
